Workbook

Sheet RECETAS
A1: Producto elaborado | B1: Insumo | C1: cantidad x unidad | D1: Costos | E1: Costo Total | F1: CMV | G1: Porcentaje | H1: Rentabilidad | I1: Markup | J1: Utilidad Bruta
A2: CHEESE BACON | B2: Blend de carne | C2: 220 | D2: =IFERROR(VLOOKUP(B2, FINANCIERO!A:D, 4, FALSE), "") -> 12.925 | E2: =C2*D2 -> 2843.5 | G2: =IF(F2=0, "", E2 / F2)
A3: CHEESE BACON | B3: cheedar feteado Milkaut | C3: 3 | D3: =IFERROR(VLOOKUP(B3, FINANCIERO!A:D, 4, FALSE), "") -> 225.53993 | E3: =C3*D3 -> 676.61979 | G3: =IF(F3=0, "", E3 / F3)
A4: CHEESE BACON | B4: Pan TBB | C4: 1 | D4: =IFERROR(VLOOKUP(B4, FINANCIERO!A:D, 4, FALSE), "") -> 648 | E4: =C4*D4 -> 648 | G4: =IF(F4=0, "", E4 / F4)
A5: CHEESE BACON | B5: Bacon | C5: 15 | D5: =IFERROR(VLOOKUP(B5, FINANCIERO!A:D, 4, FALSE), "") -> 5.63326 | E5: =C5*D5 -> 84.4989 | G5: =IF(F5=0, "", E5 / F5)
A6: CHEESE BACON | B6: Papas bastón SIMPLOT Extra Crunch | C6: 193 | D6: =IFERROR(VLOOKUP(B6, FINANCIERO!A:D, 4, FALSE), "") -> 3.4688413 | E6: =C6*D6 -> 669.48638 | G6: =IF(F6=0, "", E6 / F6)
A7: CHEESE BACON | B7: Parafinado Zoso LOTTA Burgers | C7: 1 | D7: =IFERROR(VLOOKUP(B7, FINANCIERO!A:D, 4, FALSE), "") -> 66.987179 | E7: =C7*D7 -> 66.987179 | G7: =IF(F7=0, "", E7 / F7)
A8: CHEESE BACON | B8: Sobre de papas fritas LOTTA | C8: 1 | D8: =IFERROR(VLOOKUP(B8, FINANCIERO!A:D, 4, FALSE), "") -> 35.909091 | E8: =C8*D8 -> 35.909091 | G8: =IF(F8=0, "", E8 / F8)
A9: CHEESE BACON | B9: Dips con tapa | C9: 1 | D9: =IFERROR(VLOOKUP(B9, FINANCIERO!A:D, 4, FALSE), "") -> 103.404 | E9: =C9*D9 -> 103.404 | G9: =IF(F9=0, "", E9 / F9)
A10: CHEESE BACON | B10: Salsa de Dips | C10: 1 | D10: =IFERROR(VLOOKUP(B10, FINANCIERO!A:D, 4, FALSE), "") -> 5.37514 | E10: =C10*D10 -> 5.37514 | G10: =IF(F10=0, "", E10 / F10)
A11: CHEESE BACON | B11: Servilletas | C11: 2 | D11: =IFERROR(VLOOKUP(B11, FINANCIERO!A:D, 4, FALSE), "") -> 24.625 | E11: =C11*D11 -> 49.25 | G11: =IF(F11=0, "", E11 / F11)
D12: =IFERROR(VLOOKUP(B12, FINANCIERO!A:D, 4, FALSE), "") | E12: =SUM(E2:E11) -> 5183.0305 | F12: 13900 | G12: =IF(F12=0, "", E12 / F12) -> 0.37287989 | H12: =100%-G12 -> 0.62712011 | I12: =(F12-E12)/E12*100 -> 168.18287 | J12: =F12-E12 -> 8716.9695
A13: BALDE DE MINI BURGERS | B13: Blend de carne | C13: 210 | D13: =IFERROR(VLOOKUP(B13, FINANCIERO!A:D, 4, FALSE), "") -> 12.925 | E13: =C13*D13 -> 2714.25 | G13: =IF(F13=0, "", E13 / F13)
A14: BALDE DE MINI BURGERS | B14: Pan chiquito 40 gr | C14: 6 | D14: =IFERROR(VLOOKUP(B14, FINANCIERO!A:D, 4, FALSE), "") -> 250 | E14: =C14*D14 -> 1500 | G14: =IF(F14=0, "", E14 / F14)
A15: BALDE DE MINI BURGERS | B15: Cheedar feteado Milkaut | C15: 3 | D15: =IFERROR(VLOOKUP(B15, FINANCIERO!A:D, 4, FALSE), "") -> 225.53993 | E15: =C15*D15 -> 676.61979 | G15: =IF(F15=0, "", E15 / F15)
A16: BALDE DE MINI BURGERS | B16: Cheddar liquido | C16: 70 | D16: =IFERROR(VLOOKUP(B16, FINANCIERO!A:D, 4, FALSE), "") -> 7.2801429 | E16: =C16*D16 -> 509.61 | G16: =IF(F16=0, "", E16 / F16)
A17: BALDE DE MINI BURGERS | B17: Tacita polipapel | C17: 1 | D17: =IFERROR(VLOOKUP(B17, FINANCIERO!A:D, 4, FALSE), "") -> 250 | E17: =C17*D17 -> 250 | G17: =IF(F17=0, "", E17 / F17)
A18: BALDE DE MINI BURGERS | B18: Balde de polipapel | C18: 1 | D18: =IFERROR(VLOOKUP(B18, FINANCIERO!A:D, 4, FALSE), "") -> 250 | E18: =C18*D18 -> 250 | G18: =IF(F18=0, "", E18 / F18)
D19: =IFERROR(VLOOKUP(B19, FINANCIERO!A:D, 4, FALSE), "") | E19: =SUM(E13:E18) -> 5900.4798 | F19: 15000 | G19: =IF(F19=0, "", E19 / F19) -> 0.39336532 | H19: =100%-G19 -> 0.60663468 | I19: =(F19-E19)/E19*100 -> 154.21662 | J19: =F19-E19 -> 9099.5202
A20: CHEESE BACON (SIMPLE) | B20: Blend de carne | C20: 110 | D20: =IFERROR(VLOOKUP(B20, FINANCIERO!A:D, 4, FALSE), "") -> 12.925 | E20: =C20*D20 -> 1421.75 | G20: =IF(F20=0, "", E20 / F20)
A21: CHEESE BACON (SIMPLE) | B21: cheedar feteado Milkaut | C21: 2 | D21: =IFERROR(VLOOKUP(B21, FINANCIERO!A:D, 4, FALSE), "") -> 225.53993 | E21: =C21*D21 -> 451.07986 | G21: =IF(F21=0, "", E21 / F21)
A22: CHEESE BACON (SIMPLE) | B22: Pan TBB | C22: 1 | D22: =IFERROR(VLOOKUP(B22, FINANCIERO!A:D, 4, FALSE), "") -> 648 | E22: =C22*D22 -> 648 | G22: =IF(F22=0, "", E22 / F22)
A23: CHEESE BACON (SIMPLE) | B23: Bacon | C23: 15 | D23: =IFERROR(VLOOKUP(B23, FINANCIERO!A:D, 4, FALSE), "") -> 5.63326 | E23: =C23*D23 -> 84.4989 | G23: =IF(F23=0, "", E23 / F23)
A24: CHEESE BACON (SIMPLE) | B24: Papas bastón SIMPLOT Extra Crunch | C24: 193 | D24: =IFERROR(VLOOKUP(B24, FINANCIERO!A:D, 4, FALSE), "") -> 3.4688413 | E24: =C24*D24 -> 669.48638 | G24: =IF(F24=0, "", E24 / F24)
A25: CHEESE BACON (SIMPLE) | B25: Parafinado Zoso LOTTA Burgers | C25: 1 | D25: =IFERROR(VLOOKUP(B25, FINANCIERO!A:D, 4, FALSE), "") -> 66.987179 | E25: =C25*D25 -> 66.987179 | G25: =IF(F25=0, "", E25 / F25)
A26: CHEESE BACON (SIMPLE) | B26: Sobre de papas fritas LOTTA | C26: 1 | D26: =IFERROR(VLOOKUP(B26, FINANCIERO!A:D, 4, FALSE), "") -> 35.909091 | E26: =C26*D26 -> 35.909091 | G26: =IF(F26=0, "", E26 / F26)
A27: CHEESE BACON (SIMPLE) | B27: Dips con tapa | C27: 1 | D27: =IFERROR(VLOOKUP(B27, FINANCIERO!A:D, 4, FALSE), "") -> 103.404 | E27: =C27*D27 -> 103.404 | G27: =IF(F27=0, "", E27 / F27)
A28: CHEESE BACON (SIMPLE) | B28: Salsa de Dips | C28: 1 | D28: =IFERROR(VLOOKUP(B28, FINANCIERO!A:D, 4, FALSE), "") -> 5.37514 | E28: =C28*D28 -> 5.37514 | G28: =IF(F28=0, "", E28 / F28)
A29: CHEESE BACON (SIMPLE) | B29: Servilletas | C29: 2 | D29: =IFERROR(VLOOKUP(B29, FINANCIERO!A:D, 4, FALSE), "") -> 24.625 | E29: =C29*D29 -> 49.25 | G29: =IF(F29=0, "", E29 / F29)
D30: =IFERROR(VLOOKUP(B30, FINANCIERO!A:D, 4, FALSE), "") | E30: =SUM(E20:E29) -> 3535.7405 | F30: 11000 | G30: =IF(F30=0, "", E30 / F30) -> 0.32143096 | H30: =100%-G30 -> 0.67856904 | I30: =(F30-E30)/E30*100 -> 211.1088 | J30: =F30-E30 -> 7464.2595
A31: CHEESE BURGER | B31: Blend de carne | C31: 220 | D31: =IFERROR(VLOOKUP(B31, FINANCIERO!A:D, 4, FALSE), "") -> 12.925 | E31: =C31*D31 -> 2843.5 | G31: =IF(F31=0, "", E31 / F31)
A32: CHEESE BURGER | B32: cheedar feteado Milkaut | C32: 3 | D32: =IFERROR(VLOOKUP(B32, FINANCIERO!A:D, 4, FALSE), "") -> 225.53993 | E32: =C32*D32 -> 676.61979 | G32: =IF(F32=0, "", E32 / F32)
A33: CHEESE BURGER | B33: Pan TBB | C33: 1 | D33: =IFERROR(VLOOKUP(B33, FINANCIERO!A:D, 4, FALSE), "") -> 648 | E33: =C33*D33 -> 648 | G33: =IF(F33=0, "", E33 / F33)
A34: CHEESE BURGER | B34: Papas bastón SIMPLOT Extra Crunch | C34: 193 | D34: =IFERROR(VLOOKUP(B34, FINANCIERO!A:D, 4, FALSE), "") -> 3.4688413 | E34: =C34*D34 -> 669.48638 | G34: =IF(F34=0, "", E34 / F34)
A35: CHEESE BURGER | B35: Parafinado Zoso LOTTA Burgers | C35: 1 | D35: =IFERROR(VLOOKUP(B35, FINANCIERO!A:D, 4, FALSE), "") -> 66.987179 | E35: =C35*D35 -> 66.987179 | G35: =IF(F35=0, "", E35 / F35)
A36: CHEESE BURGER | B36: Sobre de papas fritas LOTTA | C36: 1 | D36: =IFERROR(VLOOKUP(B36, FINANCIERO!A:D, 4, FALSE), "") -> 35.909091 | E36: =C36*D36 -> 35.909091 | G36: =IF(F36=0, "", E36 / F36)
A37: CHEESE BURGER | B37: Dips con tapa | C37: 1 | D37: =IFERROR(VLOOKUP(B37, FINANCIERO!A:D, 4, FALSE), "") -> 103.404 | E37: =C37*D37 -> 103.404 | G37: =IF(F37=0, "", E37 / F37)
A38: CHEESE BURGER | B38: Salsa de Dips | C38: 1 | D38: =IFERROR(VLOOKUP(B38, FINANCIERO!A:D, 4, FALSE), "") -> 5.37514 | E38: =C38*D38 -> 5.37514 | G38: =IF(F38=0, "", E38 / F38)
A39: CHEESE BURGER | B39: Servilletas | C39: 1 | D39: =IFERROR(VLOOKUP(B39, FINANCIERO!A:D, 4, FALSE), "") -> 24.625 | E39: =C39*D39 -> 24.625 | G39: =IF(F39=0, "", E39 / F39)
D40: =IFERROR(VLOOKUP(B40, FINANCIERO!A:D, 4, FALSE), "") | E40: =SUM(E31:E39) -> 5073.9066 | F40: 9000 | G40: =IF(F40=0, "", E40 / F40) -> 0.5637674 | H40: =100%-G40 -> 0.4362326 | I40: =(F40-E40)/E40*100 -> 77.378118 | J40: =F40-E40 -> 3926.0934
A41: DOBLE CUARTO | B41: Blend de carne | C41: 220 | D41: =IFERROR(VLOOKUP(B41, FINANCIERO!A:D, 4, FALSE), "") -> 12.925 | E41: =C41*D41 -> 2843.5 | G41: =IF(F41=0, "", E41 / F41)
A42: DOBLE CUARTO | B42: Bacon | C42: 15 | D42: =IFERROR(VLOOKUP(B42, FINANCIERO!A:D, 4, FALSE), "") -> 5.63326 | E42: =C42*D42 -> 84.4989 | G42: =IF(F42=0, "", E42 / F42)
A43: DOBLE CUARTO | B43: cheedar feteado Milkaut | C43: 3 | D43: =IFERROR(VLOOKUP(B43, FINANCIERO!A:D, 4, FALSE), "") -> 225.53993 | E43: =C43*D43 -> 676.61979 | G43: =IF(F43=0, "", E43 / F43)
A44: DOBLE CUARTO | B44: Pan TBB | C44: 1 | D44: =IFERROR(VLOOKUP(B44, FINANCIERO!A:D, 4, FALSE), "") -> 648 | E44: =C44*D44 -> 648 | G44: =IF(F44=0, "", E44 / F44)
A45: DOBLE CUARTO | B45: Cebolla picada | C45: 5 | D45: =IFERROR(VLOOKUP(B45, FINANCIERO!A:D, 4, FALSE), "") | E45: =C45*D45 -> #VALUE! | G45: =IF(F45=0, "", E45 / F45)
A46: DOBLE CUARTO | B46: Mostaza | C46: 5 | D46: =IFERROR(VLOOKUP(B46, FINANCIERO!A:D, 4, FALSE), "") | E46: =C46*D46 -> #VALUE! | G46: =IF(F46=0, "", E46 / F46)
A47: DOBLE CUARTO | B47: Ketchup | C47: 5 | D47: =IFERROR(VLOOKUP(B47, FINANCIERO!A:D, 4, FALSE), "") | E47: =C47*D47 -> #VALUE! | G47: =IF(F47=0, "", E47 / F47)
A48: DOBLE CUARTO | B48: Papas bastón SIMPLOT Extra Crunch | C48: 193 | D48: =IFERROR(VLOOKUP(B48, FINANCIERO!A:D, 4, FALSE), "") -> 3.4688413 | E48: =C48*D48 -> 669.48638 | G48: =IF(F48=0, "", E48 / F48)
A49: DOBLE CUARTO | B49: Parafinado Zoso LOTTA Burgers | C49: 1 | D49: =IFERROR(VLOOKUP(B49, FINANCIERO!A:D, 4, FALSE), "") -> 66.987179 | E49: =C49*D49 -> 66.987179 | G49: =IF(F49=0, "", E49 / F49)
A50: DOBLE CUARTO | B50: Sobre de papas fritas LOTTA | C50: 5 | D50: =IFERROR(VLOOKUP(B50, FINANCIERO!A:D, 4, FALSE), "") -> 35.909091 | E50: =C50*D50 -> 179.54545 | G50: =IF(F50=0, "", E50 / F50)
A51: DOBLE CUARTO | B51: Dips con tapa | C51: 1 | D51: =IFERROR(VLOOKUP(B51, FINANCIERO!A:D, 4, FALSE), "") -> 103.404 | E51: =C51*D51 -> 103.404 | G51: =IF(F51=0, "", E51 / F51)
A52: DOBLE CUARTO | B52: Salsa de Dips | C52: 1 | D52: =IFERROR(VLOOKUP(B52, FINANCIERO!A:D, 4, FALSE), "") -> 5.37514 | E52: =C52*D52 -> 5.37514 | G52: =IF(F52=0, "", E52 / F52)
A53: DOBLE CUARTO | B53: Servilletas | C53: 2 | D53: =IFERROR(VLOOKUP(B53, FINANCIERO!A:D, 4, FALSE), "") -> 24.625 | E53: =C53*D53 -> 49.25 | G53: =IF(F53=0, "", E53 / F53)
D54: =IFERROR(VLOOKUP(B54, FINANCIERO!A:D, 4, FALSE), "") | E54: =SUM(E41:E53) -> #VALUE! | F54: 13900 | G54: =IF(F54=0, "", E54 / F54) -> #VALUE! | H54: =100%-G54 -> #VALUE! | I54: =(F54-E54)/E54*100 -> #VALUE! | J54: =F54-E54 -> #VALUE!
A55: ONION RINGS BURGER | B55: Blend de carne | C55: 220 | D55: =IFERROR(VLOOKUP(B55, FINANCIERO!A:D, 4, FALSE), "") -> 12.925 | E55: =C55*D55 -> 2843.5 | G55: =IF(F55=0, "", E55 / F55)
A56: ONION RINGS BURGER | B56: Bacon | C56: 15 | D56: =IFERROR(VLOOKUP(B56, FINANCIERO!A:D, 4, FALSE), "") -> 5.63326 | E56: =C56*D56 -> 84.4989 | G56: =IF(F56=0, "", E56 / F56)
A57: ONION RINGS BURGER | B57: cheedar feteado Milkaut | C57: 3 | D57: =IFERROR(VLOOKUP(B57, FINANCIERO!A:D, 4, FALSE), "") -> 225.53993 | E57: =C57*D57 -> 676.61979 | G57: =IF(F57=0, "", E57 / F57)
A58: ONION RINGS BURGER | B58: Pan TBB | C58: 1 | D58: =IFERROR(VLOOKUP(B58, FINANCIERO!A:D, 4, FALSE), "") -> 648 | E58: =C58*D58 -> 648 | G58: =IF(F58=0, "", E58 / F58)
A59: ONION RINGS BURGER | B59: Aros de Cebolla | C59: 50 | D59: =IFERROR(VLOOKUP(B59, FINANCIERO!A:D, 4, FALSE), "") -> 9.18121 | E59: =C59*D59 -> 459.0605 | G59: =IF(F59=0, "", E59 / F59)
A60: ONION RINGS BURGER | B60: Barbacoa | C60: 5 | D60: =IFERROR(VLOOKUP(B60, FINANCIERO!A:D, 4, FALSE), "") -> 3.6156667 | E60: =C60*D60 -> 18.078333 | G60: =IF(F60=0, "", E60 / F60)
A61: ONION RINGS BURGER | B61: Papas bastón SIMPLOT Extra Crunch | C61: 193 | D61: =IFERROR(VLOOKUP(B61, FINANCIERO!A:D, 4, FALSE), "") -> 3.4688413 | E61: =C61*D61 -> 669.48638 | G61: =IF(F61=0, "", E61 / F61)
A62: ONION RINGS BURGER | B62: Parafinado Zoso LOTTA Burgers | C62: 1 | D62: =IFERROR(VLOOKUP(B62, FINANCIERO!A:D, 4, FALSE), "") -> 66.987179 | E62: =C62*D62 -> 66.987179 | G62: =IF(F62=0, "", E62 / F62)
A63: ONION RINGS BURGER | B63: Sobre de papas fritas LOTTA | C63: 1 | D63: =IFERROR(VLOOKUP(B63, FINANCIERO!A:D, 4, FALSE), "") -> 35.909091 | E63: =C63*D63 -> 35.909091 | G63: =IF(F63=0, "", E63 / F63)
A64: ONION RINGS BURGER | B64: Dips con tapa | C64: 1 | D64: =IFERROR(VLOOKUP(B64, FINANCIERO!A:D, 4, FALSE), "") -> 103.404 | E64: =C64*D64 -> 103.404 | G64: =IF(F64=0, "", E64 / F64)
A65: ONION RINGS BURGER | B65: Salsa de Dips | C65: 1 | D65: =IFERROR(VLOOKUP(B65, FINANCIERO!A:D, 4, FALSE), "") -> 5.37514 | E65: =C65*D65 -> 5.37514 | G65: =IF(F65=0, "", E65 / F65)
A66: ONION RINGS BURGER | B66: Servilletas | C66: 2 | D66: =IFERROR(VLOOKUP(B66, FINANCIERO!A:D, 4, FALSE), "") -> 24.625 | E66: =C66*D66 -> 49.25 | G66: =IF(F66=0, "", E66 / F66)
D67: =IFERROR(VLOOKUP(B67, FINANCIERO!A:D, 4, FALSE), "") | E67: =SUM(E55:E66) -> 5660.1693 | F67: 13900 | G67: =IF(F67=0, "", E67 / F67) -> 0.40720643 | H67: =100%-G67 -> 0.59279357 | I67: =(F67-E67)/E67*100 -> 145.57569 | J67: =F67-E67 -> 8239.8307
A68: TASTY WLB | B68: Blend de carne | C68: 220 | D68: =IFERROR(VLOOKUP(B68, FINANCIERO!A:D, 4, FALSE), "") -> 12.925 | E68: =C68*D68 -> 2843.5 | G68: =IF(F68=0, "", E68 / F68)
A69: TASTY WLB | B69: cheedar feteado Milkaut | C69: 3 | D69: =IFERROR(VLOOKUP(B69, FINANCIERO!A:D, 4, FALSE), "") -> 225.53993 | E69: =C69*D69 -> 676.61979 | G69: =IF(F69=0, "", E69 / F69)
A70: TASTY WLB | B70: Pan TBB | C70: 1 | D70: =IFERROR(VLOOKUP(B70, FINANCIERO!A:D, 4, FALSE), "") -> 648 | E70: =C70*D70 -> 648 | G70: =IF(F70=0, "", E70 / F70)
A71: TASTY WLB | B71: Cebolla | C71: 10 | D71: =IFERROR(VLOOKUP(B71, FINANCIERO!A:D, 4, FALSE), "") -> 0.75 | E71: =C71*D71 -> 7.5 | G71: =IF(F71=0, "", E71 / F71)
A72: TASTY WLB | B72: Lechuga | C72: 20 | D72: =IFERROR(VLOOKUP(B72, FINANCIERO!A:D, 4, FALSE), "") -> 5 | E72: =C72*D72 -> 100 | G72: =IF(F72=0, "", E72 / F72)
A73: TASTY WLB | B73: Tomate | C73: 30 | D73: =IFERROR(VLOOKUP(B73, FINANCIERO!A:D, 4, FALSE), "") -> 3.5 | E73: =C73*D73 -> 105 | G73: =IF(F73=0, "", E73 / F73)
A74: TASTY WLB | B74: Salsa TASTY | C74: 10 | D74: =IFERROR(VLOOKUP(B74, FINANCIERO!A:D, 4, FALSE), "") -> 10 | E74: =C74*D74 -> 100 | G74: =IF(F74=0, "", E74 / F74)
A75: TASTY WLB | B75: Papas bastón SIMPLOT Extra Crunch | C75: 193 | D75: =IFERROR(VLOOKUP(B75, FINANCIERO!A:D, 4, FALSE), "") -> 3.4688413 | E75: =C75*D75 -> 669.48638 | G75: =IF(F75=0, "", E75 / F75)
A76: TASTY WLB | B76: Parafinado Zoso LOTTA Burgers | C76: 1 | D76: =IFERROR(VLOOKUP(B76, FINANCIERO!A:D, 4, FALSE), "") -> 66.987179 | E76: =C76*D76 -> 66.987179 | G76: =IF(F76=0, "", E76 / F76)
A77: TASTY WLB | B77: Sobre de papas fritas LOTTA | C77: 1 | D77: =IFERROR(VLOOKUP(B77, FINANCIERO!A:D, 4, FALSE), "") -> 35.909091 | E77: =C77*D77 -> 35.909091 | G77: =IF(F77=0, "", E77 / F77)
A78: TASTY WLB | B78: Dips con tapa | C78: 1 | D78: =IFERROR(VLOOKUP(B78, FINANCIERO!A:D, 4, FALSE), "") -> 103.404 | E78: =C78*D78 -> 103.404 | G78: =IF(F78=0, "", E78 / F78)
A79: TASTY WLB | B79: Salsa de Dips | C79: 1 | D79: =IFERROR(VLOOKUP(B79, FINANCIERO!A:D, 4, FALSE), "") -> 5.37514 | E79: =C79*D79 -> 5.37514 | G79: =IF(F79=0, "", E79 / F79)
A80: TASTY WLB | B80: Servilletas | C80: 2 | D80: =IFERROR(VLOOKUP(B80, FINANCIERO!A:D, 4, FALSE), "") -> 24.625 | E80: =C80*D80 -> 49.25 | G80: =IF(F80=0, "", E80 / F80)
D81: =IFERROR(VLOOKUP(B81, FINANCIERO!A:D, 4, FALSE), "") | E81: =SUM(E68:E80) -> 5411.0316 | F81: 13900 | G81: =IF(F81=0, "", E81 / F81) -> 0.38928285 | H81: =100%-G81 -> 0.61071715 | I81: =(F81-E81)/E81*100 -> 156.88263 | J81: =F81-E81 -> 8488.9684
A82: SWEET ONION | B82: Blend de carne | C82: 220 | D82: =IFERROR(VLOOKUP(B82, FINANCIERO!A:D, 4, FALSE), "") -> 12.925 | E82: =C82*D82 -> 2843.5 | G82: =IF(F82=0, "", E82 / F82)
A83: SWEET ONION | B83: cheedar feteado Milkaut | C83: 3 | D83: =IFERROR(VLOOKUP(B83, FINANCIERO!A:D, 4, FALSE), "") -> 225.53993 | E83: =C83*D83 -> 676.61979 | G83: =IF(F83=0, "", E83 / F83)
A84: SWEET ONION | B84: Cebolla caramelizada | C84: 30 | D84: =IFERROR(VLOOKUP(B84, FINANCIERO!A:D, 4, FALSE), "") | E84: =C84*D84 -> #VALUE! | G84: =IF(F84=0, "", E84 / F84)
A85: SWEET ONION | B85: Bacon | C85: 15 | D85: =IFERROR(VLOOKUP(B85, FINANCIERO!A:D, 4, FALSE), "") -> 5.63326 | E85: =C85*D85 -> 84.4989 | G85: =IF(F85=0, "", E85 / F85)
A86: SWEET ONION | B86: Pan TBB | C86: 1 | D86: =IFERROR(VLOOKUP(B86, FINANCIERO!A:D, 4, FALSE), "") -> 648 | E86: =C86*D86 -> 648 | G86: =IF(F86=0, "", E86 / F86)
A87: SWEET ONION | B87: Papas bastón SIMPLOT Extra Crunch | C87: 193 | D87: =IFERROR(VLOOKUP(B87, FINANCIERO!A:D, 4, FALSE), "") -> 3.4688413 | E87: =C87*D87 -> 669.48638 | G87: =IF(F87=0, "", E87 / F87)
A88: SWEET ONION | B88: Parafinado Zoso LOTTA Burgers | C88: 1 | D88: =IFERROR(VLOOKUP(B88, FINANCIERO!A:D, 4, FALSE), "") -> 66.987179 | E88: =C88*D88 -> 66.987179 | G88: =IF(F88=0, "", E88 / F88)
A89: SWEET ONION | B89: Sobre de papas fritas LOTTA | C89: 1 | D89: =IFERROR(VLOOKUP(B89, FINANCIERO!A:D, 4, FALSE), "") -> 35.909091 | E89: =C89*D89 -> 35.909091 | G89: =IF(F89=0, "", E89 / F89)
A90: SWEET ONION | B90: Dips con tapa | C90: 1 | D90: =IFERROR(VLOOKUP(B90, FINANCIERO!A:D, 4, FALSE), "") -> 103.404 | E90: =C90*D90 -> 103.404 | G90: =IF(F90=0, "", E90 / F90)
A91: SWEET ONION | B91: Salsa de Dips | C91: 1 | D91: =IFERROR(VLOOKUP(B91, FINANCIERO!A:D, 4, FALSE), "") -> 5.37514 | E91: =C91*D91 -> 5.37514 | G91: =IF(F91=0, "", E91 / F91)
A92: SWEET ONION | B92: Servilletas | C92: 2 | D92: =IFERROR(VLOOKUP(B92, FINANCIERO!A:D, 4, FALSE), "") -> 24.625 | E92: =C92*D92 -> 49.25 | G92: =IF(F92=0, "", E92 / F92)
D93: =IFERROR(VLOOKUP(B93, FINANCIERO!A:D, 4, FALSE), "") | E93: =SUM(E82:E92) -> #VALUE! | F93: 13900 | G93: =IF(F93=0, "", E93 / F93) -> #VALUE! | H93: =100%-G93 -> #VALUE! | I93: =(F93-E93)/E93*100 -> #VALUE! | J93: =F93-E93 -> #VALUE!
A94: MIGI BURGER | B94: Blend de carne | C94: 160 | D94: =IFERROR(VLOOKUP(B94, FINANCIERO!A:D, 4, FALSE), "") -> 12.925 | E94: =C94*D94 -> 2068 | G94: =IF(F94=0, "", E94 / F94)
A95: MIGI BURGER | B95: cheedar feteado Milkaut | C95: 3 | D95: =IFERROR(VLOOKUP(B95, FINANCIERO!A:D, 4, FALSE), "") -> 225.53993 | E95: =C95*D95 -> 676.61979 | G95: =IF(F95=0, "", E95 / F95)
A96: MIGI BURGER | B96: Pan chico de papa TBB | C96: 1 | D96: =IFERROR(VLOOKUP(B96, FINANCIERO!A:D, 4, FALSE), "") -> 534 | E96: =C96*D96 -> 534 | G96: =IF(F96=0, "", E96 / F96)
A97: MIGI BURGER | B97: Papas bastón SIMPLOT Extra Crunch | C97: 193 | D97: =IFERROR(VLOOKUP(B97, FINANCIERO!A:D, 4, FALSE), "") -> 3.4688413 | E97: =C97*D97 -> 669.48638 | G97: =IF(F97=0, "", E97 / F97)
A98: MIGI BURGER | B98: Parafinado Zoso LOTTA Burgers | C98: 1 | D98: =IFERROR(VLOOKUP(B98, FINANCIERO!A:D, 4, FALSE), "") -> 66.987179 | E98: =C98*D98 -> 66.987179 | G98: =IF(F98=0, "", E98 / F98)
A99: MIGI BURGER | B99: Dips con tapa | C99: 1 | D99: =IFERROR(VLOOKUP(B99, FINANCIERO!A:D, 4, FALSE), "") -> 103.404 | E99: =C99*D99 -> 103.404 | G99: =IF(F99=0, "", E99 / F99)
A100: MIGI BURGER | B100: Salsa de Dips | C100: 1 | D100: =IFERROR(VLOOKUP(B100, FINANCIERO!A:D, 4, FALSE), "") -> 5.37514 | E100: =C100*D100 -> 5.37514 | G100: =IF(F100=0, "", E100 / F100)
...

Sheet FINANCIERO
A2: Materia Prima | B2: Costo x bulto | C2: Unidad x bulto | D2: Costo unitario | E2: CHECK | F2: Actualización
A3: Blend de carne | B3: =(B39*0.5)+(B37*0.25)+(B38*0.25) -> 12925 | C3: 1000 | D3: =B3/C3 -> 12.925 | E3: TRUE | F3: 46035
A4: Blend de carne PREMIUM | B4: =(B34*0.35)+(B35*0.5)+(B36*0.15) -> 11115 | C4: 1000 | D4: =B4/C4 -> 11.115 | E4: TRUE | F4: 46058
A5: Medallon Veggie | B5: 700 | C5: 1 | D5: =C5*B5 -> 700 | E5: TRUE
A6: Bondiola de cerdo | B6: =(B29 * 2) + (B30 * 2) + (B31 * 0.5) -> 14485.82 | C6: 3000 | D6: =(B6/C6)*1 -> 4.8286067 | E6: TRUE
A7: Cheedar feteado Milkaut | B7: 129911 | C7: 576 | D7: =B7/C7 -> 225.53993 | E7: TRUE
A8: Pan chico de papa TBB | B8: 534 | C8: 1 | D8: =B8/C8 -> 534 | E8: TRUE
A9: Pan TBB | B9: 648 | C9: 1 | D9: =B9/C9 -> 648 | E9: TRUE
A10: Pan chiquito 40 gr | B10: 250 | C10: 1 | D10: =B10/C10 -> 250 | E10: TRUE | F10: 46045
A11: Papas bastón SIMPLOT Extra Crunch | B11: 52032.62 | C11: 15000 | D11: =B11/C11 -> 3.4688413 | E11: TRUE
A12: Aros de Cebolla | B12: 9181.21 | C12: 1000 | D12: =B12/C12 -> 9.18121 | E12: TRUE
A13: Nuggets de Pollo | B13: 40338.35 | C13: 3000 | D13: =B13/C13 -> 13.446117 | E13: TRUE
A14: Cheddar liquido | B14: 25480.5 | C14: 3500 | D14: =B14/C14 -> 7.2801429 | E14: TRUE | F14: 46045
A15: Bacon | B15: 5633.26 | C15: 1000 | D15: =B15/C15 -> 5.63326 | E15: TRUE
A16: Sal porción | B16: 8231.74 | C16: 1000 | D16: =B16/C16 -> 8.23174 | E16: TRUE
A17: Aceite | B17: 63000 | C17: 30 | D17: =B17/C17 -> 2100 | E17: TRUE
A18: Salsa TASTY | B18: 10000 | C18: 1000 | D18: =B18/C18 -> 10 | E18: TRUE
A19: Postre Oreo | B19: 2800 | C19: 1 | D19: =B19/C19 -> 2800 | E19: TRUE
A20: Postre Chocotorta | B20: 2800 | C20: 1 | D20: =B20/C20 -> 2800 | E20: TRUE
A21: Salsa Queso Azul | B21: 5000 | C21: 1000 | D21: =B21/C21 -> 5 | E21: FALSE
A22: Salsa WLB | B22: 10000 | C22: 1000 | D22: =B22/C22 -> 10 | E22: FALSE
A23: Huevo | B23: 6800 | C23: 30 | D23: =B23/C23 -> 226.66667 | E23: TRUE
A24: Pepino en vinagre | B24: 18000 | C24: 1500 | D24: =B24/C24 -> 12 | E24: TRUE
A25: Salsa de Dips | B25: 5375.14 | C25: 1000 | D25: =B25/C25 -> 5.37514 | E25: FALSE
A26: Ketchup pouch | B26: 10847 | C26: 3000 | D26: =B26/C26 -> 3.6156667 | E26: FALSE
... A33: Lechuga | B33: 5000 | C33: 1000 | D33: =B33/C33 -> 5 | E33: TRUE
A34: Tapa de asado (NOVILLO) | B34: 14900 | C34: 1000 | D34: =B34/C34 -> 14.9 | E34: TRUE | F34: 46058
A35: Roas Beef (NOVILLO) | B35: 11500 | C35: 1000 | D35: =B35/C35 -> 11.5 | E35: TRUE | F35: 46058
A36: Grasa de Pella | B36: 1000 | C36: 1000 | D36: =B36/C36 -> 1 | E36: TRUE | F36: 46058
A37: Tapa de asado | B37: 14300 | C37: 1000 | D37: =B37/C37 -> 14.3 | E37: TRUE | F37: 46035
A38: Falda deshuesada | B38: 11000 | C38: 1000 | D38: =B38/C38 -> 11 | E38: TRUE | F38: 46035
A39: Roast beef | B39: 13200 | C39: 1000 | D39: =B39/C39 -> 13.2 | E39: TRUE | F39: 46035
A40: Bebidas | E40: FALSE
A41: Pepsi Black | B41: 4548.6 | C41: 6 | D41: =B41/C41 -> 758.1 | E41: TRUE | F41: 46035
A42: Pepsi | B42: 4623.18 | C42: 6 | D42: =B42/C42 -> 770.53 | E42: TRUE | F42: 46035
A43: Mirinda | B43: 4548.68 | C43: 6 | D43: =B43/C43 -> 758.11333 | E43: TRUE | F43: 46035
A44: Bebida lata | B44: =(B43+B42+B41)/3 -> 4573.4867 | C44: 6 | D44: =B44/C44 -> 762.24778 | E44: TRUE | F44: 46035
A45: Cerveza tirada | B45: =(105300+215545+353295+110245+110245+245333.6)/6 -> 189993.93 | C45: 50 | D45: =B45/C45 -> 3799.8787 | E45: TRUE
A46: Pinta de cerveza | B46: =D45/2 -> 1899.9393 | C46: 1 | D46: =B46/C46 -> 1899.9393 | E46: TRUE
A47: Media Pinta de cerveza | B47: =D45/4 -> 949.96967 | C47: 1 | D47: =B47/C47 -> 949.96967 | E47: TRUE
A48: Seven-up | B48: 4548.68 | C48: 6 | D48: =B48/C48 -> 758.11333 | E48: TRUE | F48: 46035
A49: Agua mineral | B49: 11047.97 | C49: 12 | D49: =B49/C49 -> 920.66417 | E49: TRUE | F49: 46035
A50: Agua Pomelo H20 | B50: 4304.25 | C50: 6 | D50: =B50/C50 -> 717.375 | E50: TRUE | F50: 46035
A51: Agua Limón H20 | B51: 4304.25 | C51: 6 | D51: =B51/C51 -> 717.375 | E51: TRUE | F51: 46035
A52: Agua Manzana H20 | B52: 4304.15 | C52: 6 | D52: =B52/C52 -> 717.35833 | E52: TRUE | F52: 46035
A53: Packaging
A54: Papel Aluminio | B54: 90900 | C54: 700 | D54: =B54/C54 -> 129.85714 | E54: TRUE
A55: Parafinado Impreso Letras 30x35 | B55: 15517 | C55: 240 | D55: =B55/C55 -> 64.654167 | E55: TRUE
A56: Parafinado Zoso LOTTA Burgers | B56: 836000 | C56: 12480 | D56: =B56/C56 -> 66.987179 | E56: TRUE
A57: Sobre de papas fritas LOTTA | B57: 790000 | C57: 22000 | D57: =B57/C57 -> 35.909091 | E57: TRUE
A58: Botella de Cerveza | B58: 41400 | C58: 50 | D58: =B58/C58 -> 828 | E58: TRUE
A59: Caja Delivery LOTTA | B59: 390 | C59: 1 | D59: =B59/C59 -> 390 | E59: TRUE | F59: 46045
A60: Tacita polipapel | B60: 250 | C60: 1 | D60: =B60/C60 -> 250 | E60: TRUE | F60: 46045
A61: Balde de polipapel | B61: 250 | C61: 1 | D61: =B61/C61 -> 250 | E61: TRUE | F61: 46045
A62: Caja Bisagra | B62: 78642 | C62: 160 | D62: =B62/C62 -> 491.5125 | E62: TRUE
A63: Dips con tapa | B63: 10340.4 | C63: 100 | D63: =B63/C63 -> 103.404 | E63: FALSE
A64: Servilletas | B64: 24625 | C64: 1000 | D64: =B64/C64 -> 24.625 | E64: FALSE
E65: FALSE

Sheet CMV DIARIO
A1: PRODUCTOS | B1: TOTAL | C1: COSTO UNITARIO | D1: COSTO TOTAL | E1: CMV | F1: CMV
A2: DIA LABORAL | B2: 15 | C2: =PROPER(TEXT(DATE(2026, 2, B2), "dddd")) -> Domingo | E2: TURNO A | F2: TURNO B
A3: =IFERROR(__xludf.DUMMYFUNCTION("QUERY({IMPORTRANGE(""1gFO4fFAF8uaSQckGNdL2ULC0kQjiaTn7HExgq5kTGAk"",""VENTAS""&B2&""!B2:C101"");IMPORTRANGE(""1gFO4fFAF8uaSQckGNdL2ULC0kQjiaTn7HExgq5kTGAk"",""VENTAS""&B2&""!F2:G101"")},""Select Col1, sum(Col2) where Col1 is not null group by Col1 label s"&"um(Col2) 'Total'"",0)"),"") | B3: =IFERROR(__xludf.DUMMYFUNCTION("""COMPUTED_VALUE"""),"Total") -> Total
A4: =IFERROR(__xludf.DUMMYFUNCTION("""COMPUTED_VALUE"""),"AGUA MANZANA H20") -> AGUA MANZANA H20 | B4: =IFERROR(__xludf.DUMMYFUNCTION("""COMPUTED_VALUE"""),1) -> 1 | C4: =IFERROR(__xludf.DUMMYFUNCTION("INDEX(RECETAS!E:E, MAX(FILTER(ROW(RECETAS!A:A), RECETAS!A:A=A4)) + 1)"),717.358333333333) -> 717.35833 | D4: =C4*B4 -> 717.35833 | E4: =IFERROR(__xludf.DUMMYFUNCTION("IFNA(FILTER('Febrero 2026'!C3:D34, 'Febrero 2026'!B3:B34 = B2), ""Fecha no encontrada"")"),288800) -> 288800 | F4: =IFERROR(__xludf.DUMMYFUNCTION("""COMPUTED_VALUE"""),315500) -> 315500
A5: =IFERROR(__xludf.DUMMYFUNCTION("""COMPUTED_VALUE"""),"AGUA MINERAL") -> AGUA MINERAL | B5: =IFERROR(__xludf.DUMMYFUNCTION("""COMPUTED_VALUE"""),4) -> 4 | C5: =IFERROR(__xludf.DUMMYFUNCTION("INDEX(RECETAS!E:E, MAX(FILTER(ROW(RECETAS!A:A), RECETAS!A:A=A5)) + 1)"),920.664166666666) -> 920.66417 | D5: =C5*B5 -> 3682.6567
A6: =IFERROR(__xludf.DUMMYFUNCTION("""COMPUTED_VALUE"""),"AGUA POMELO H20") -> AGUA POMELO H20 | B6: =IFERROR(__xludf.DUMMYFUNCTION("""COMPUTED_VALUE"""),1) -> 1 | C6: =IFERROR(__xludf.DUMMYFUNCTION("INDEX(RECETAS!E:E, MAX(FILTER(ROW(RECETAS!A:A), RECETAS!A:A=A6)) + 1)"),717.375) -> 717.375 | D6: =C6*B6 -> 717.375
A7: =IFERROR(__xludf.DUMMYFUNCTION("""COMPUTED_VALUE"""),"AMERICAN BURGER") -> AMERICAN BURGER | B7: =IFERROR(__xludf.DUMMYFUNCTION("""COMPUTED_VALUE"""),3) -> 3 | C7: =IFERROR(__xludf.DUMMYFUNCTION("INDEX(RECETAS!E:E, MAX(FILTER(ROW(RECETAS!A:A), RECETAS!A:A=A7)) + 1)"),5886.03157939627) -> 5886.0316 | D7: =C7*B7 -> 17658.095
A8: =IFERROR(__xludf.DUMMYFUNCTION("""COMPUTED_VALUE"""),"BLUE CHEESE") -> BLUE CHEESE | B8: =IFERROR(__xludf.DUMMYFUNCTION("""COMPUTED_VALUE"""),1) -> 1 | C8: =IFERROR(__xludf.DUMMYFUNCTION("INDEX(RECETAS!E:E, MAX(FILTER(ROW(RECETAS!A:A), RECETAS!A:A=A8)) + 1)"),5298.53157939627) -> 5298.5316 | D8: =C8*B8 -> 5298.5316
A9: =IFERROR(__xludf.DUMMYFUNCTION("""COMPUTED_VALUE"""),"CHEESE BACON") -> CHEESE BACON | B9: =IFERROR(__xludf.DUMMYFUNCTION("""COMPUTED_VALUE"""),10) -> 10 | C9: =IFERROR(__xludf.DUMMYFUNCTION("INDEX(RECETAS!E:E, MAX(FILTER(ROW(RECETAS!A:A), RECETAS!A:A=A9)) + 1)"),5183.03047939627) -> 5183.0305 | D9: =C9*B9 -> 51830.305
A10: =IFERROR(__xludf.DUMMYFUNCTION("""COMPUTED_VALUE"""),"DOBLE CUARTO") -> DOBLE CUARTO | B10: =IFERROR(__xludf.DUMMYFUNCTION("""COMPUTED_VALUE"""),1) -> 1 | C10: =IFERROR(__xludf.DUMMYFUNCTION("INDEX(RECETAS!E:E, MAX(FILTER(ROW(RECETAS!A:A), RECETAS!A:A=A10)) + 1)"),5326.66684303263) -> 5326.6668 | D10: =C10*B10 -> 5326.6668
A11: =IFERROR(__xludf.DUMMYFUNCTION("""COMPUTED_VALUE"""),"EXTRA MEDALLON") -> EXTRA MEDALLON | B11: =IFERROR(__xludf.DUMMYFUNCTION("""COMPUTED_VALUE"""),3) -> 3 | C11: =IFERROR(__xludf.DUMMYFUNCTION("INDEX(RECETAS!E:E, MAX(FILTER(ROW(RECETAS!A:A), RECETAS!A:A=A11)) + 1)"),1421.75) -> 1421.75 | D11: =C11*B11 -> 4265.25
A12: =IFERROR(__xludf.DUMMYFUNCTION("""COMPUTED_VALUE"""),"HUMPTY BURGER") -> HUMPTY BURGER | B12: =IFERROR(__xludf.DUMMYFUNCTION("""COMPUTED_VALUE"""),6) -> 6 | C12: =IFERROR(__xludf.DUMMYFUNCTION("INDEX(RECETAS!E:E, MAX(FILTER(ROW(RECETAS!A:A), RECETAS!A:A=A12)) + 1)"),5409.69714606293) -> 5409.6971 | D12: =C12*B12 -> 32458.183
A13: =IFERROR(__xludf.DUMMYFUNCTION("""COMPUTED_VALUE"""),"JIMMY BURGER") -> JIMMY BURGER | B13: =IFERROR(__xludf.DUMMYFUNCTION("""COMPUTED_VALUE"""),1) -> 1 | C13: =IFERROR(__xludf.DUMMYFUNCTION("INDEX(RECETAS!E:E, MAX(FILTER(ROW(RECETAS!A:A), RECETAS!A:A=A13)) + 1)"),3923.49054884071) -> 3923.4905 | D13: =C13*B13 -> 3923.4905
A14: =IFERROR(__xludf.DUMMYFUNCTION("""COMPUTED_VALUE"""),"MIGI BURGER") -> MIGI BURGER | B14: =IFERROR(__xludf.DUMMYFUNCTION("""COMPUTED_VALUE"""),2) -> 2 | C14: =IFERROR(__xludf.DUMMYFUNCTION("INDEX(RECETAS!E:E, MAX(FILTER(ROW(RECETAS!A:A), RECETAS!A:A=A14)) + 1)"),4209.03157939627) -> 4209.0316 | D14: =C14*B14 -> 8418.0632
A15: =IFERROR(__xludf.DUMMYFUNCTION("""COMPUTED_VALUE"""),"MIRINDA") -> MIRINDA | B15: =IFERROR(__xludf.DUMMYFUNCTION("""COMPUTED_VALUE"""),1) -> 1 | C15: =IFERROR(__xludf.DUMMYFUNCTION("INDEX(RECETAS!E:E, MAX(FILTER(ROW(RECETAS!A:A), RECETAS!A:A=A15)) + 1)"),758.113333333333) -> 758.11333 | D15: =C15*B15 -> 758.11333
A16: =IFERROR(__xludf.DUMMYFUNCTION("""COMPUTED_VALUE"""),"MOBY DICK") -> MOBY DICK | B16: =IFERROR(__xludf.DUMMYFUNCTION("""COMPUTED_VALUE"""),1) -> 1 | C16: =IFERROR(__xludf.DUMMYFUNCTION("INDEX(RECETAS!E:E, MAX(FILTER(ROW(RECETAS!A:A), RECETAS!A:A=A16)) + 1)"),8562.10924050738) -> 8562.1092 | D16: =C16*B16 -> 8562.1092
A17: =IFERROR(__xludf.DUMMYFUNCTION("""COMPUTED_VALUE"""),"NUGGETS X 6") -> NUGGETS X 6 | B17: =IFERROR(__xludf.DUMMYFUNCTION("""COMPUTED_VALUE"""),1) -> 1 | C17: =IFERROR(__xludf.DUMMYFUNCTION("INDEX(RECETAS!E:E, MAX(FILTER(ROW(RECETAS!A:A), RECETAS!A:A=A17)) + 1)"),1680.52117948717) -> 1680.5212 | D17: =C17*B17 -> 1680.5212
A18: =IFERROR(__xludf.DUMMYFUNCTION("""COMPUTED_VALUE"""),"ONION RINGS BURGER") -> ONION RINGS BURGER | B18: =IFERROR(__xludf.DUMMYFUNCTION("""COMPUTED_VALUE"""),2) -> 2 | C18: =IFERROR(__xludf.DUMMYFUNCTION("INDEX(RECETAS!E:E, MAX(FILTER(ROW(RECETAS!A:A), RECETAS!A:A=A18)) + 1)"),5660.1693127296) -> 5660.1693 | D18: =C18*B18 -> 11320.339
A19: =IFERROR(__xludf.DUMMYFUNCTION("""COMPUTED_VALUE"""),"PEPSI ") -> PEPSI | B19: =IFERROR(__xludf.DUMMYFUNCTION("""COMPUTED_VALUE"""),3) -> 3 | C19: =IFERROR(__xludf.DUMMYFUNCTION("INDEX(RECETAS!E:E, MAX(FILTER(ROW(RECETAS!A:A), RECETAS!A:A=A19)) + 1)"),770.53) -> 770.53 | D19: =C19*B19 -> 2311.59
A20: =IFERROR(__xludf.DUMMYFUNCTION("""COMPUTED_VALUE"""),"PORCION DE PAPAS") -> PORCION DE PAPAS | B20: =IFERROR(__xludf.DUMMYFUNCTION("""COMPUTED_VALUE"""),1) -> 1 | C20: =IFERROR(__xludf.DUMMYFUNCTION("INDEX(RECETAS!E:E, MAX(FILTER(ROW(RECETAS!A:A), RECETAS!A:A=A20)) + 1)"),2292.92034615384) -> 2292.9203 | D20: =C20*B20 -> 2292.9203
A21: =IFERROR(__xludf.DUMMYFUNCTION("""COMPUTED_VALUE"""),"PULLED PORK") -> PULLED PORK | B21: =IFERROR(__xludf.DUMMYFUNCTION("""COMPUTED_VALUE"""),2) -> 2 | C21: =IFERROR(__xludf.DUMMYFUNCTION("INDEX(RECETAS!E:E, MAX(FILTER(ROW(RECETAS!A:A), RECETAS!A:A=A21)) + 1)"),2652.60312106293) -> 2652.6031 | D21: =C21*B21 -> 5305.2062
A22: =IFERROR(__xludf.DUMMYFUNCTION("""COMPUTED_VALUE"""),"SEVEN-UP") -> SEVEN-UP | B22: =IFERROR(__xludf.DUMMYFUNCTION("""COMPUTED_VALUE"""),5) -> 5 | C22: =IFERROR(__xludf.DUMMYFUNCTION("INDEX(RECETAS!E:E, MAX(FILTER(ROW(RECETAS!A:A), RECETAS!A:A=A22)) + 1)"),758.113333333333) -> 758.11333 | D22: =C22*B22 -> 3790.5667
A23: =IFERROR(__xludf.DUMMYFUNCTION("""COMPUTED_VALUE"""),"SWEET BACON BURGER") -> SWEET BACON BURGER | B23: =IFERROR(__xludf.DUMMYFUNCTION("""COMPUTED_VALUE"""),1) -> 1 | C23: =IFERROR(__xludf.DUMMYFUNCTION("INDEX(RECETAS!E:E, MAX(FILTER(ROW(RECETAS!A:A), RECETAS!A:A=A23)) + 1)"),5148.53157939627) -> 5148.5316 | D23: =C23*B23 -> 5148.5316
A24: =IFERROR(__xludf.DUMMYFUNCTION("""COMPUTED_VALUE"""),"SWEET ONION") -> SWEET ONION | B24: =IFERROR(__xludf.DUMMYFUNCTION("""COMPUTED_VALUE"""),5) -> 5 | C24: =IFERROR(__xludf.DUMMYFUNCTION("INDEX(RECETAS!E:E, MAX(FILTER(ROW(RECETAS!A:A), RECETAS!A:A=A24)) + 1)"),5183.03047939627) -> 5183.0305 | D24: =C24*B24 -> 25915.152
A25: =IFERROR(__xludf.DUMMYFUNCTION("""COMPUTED_VALUE"""),"TASTY WLB") -> TASTY WLB | B25: =IFERROR(__xludf.DUMMYFUNCTION("""COMPUTED_VALUE"""),1) -> 1 | C25: =IFERROR(__xludf.DUMMYFUNCTION("INDEX(RECETAS!E:E, MAX(FILTER(ROW(RECETAS!A:A), RECETAS!A:A=A25)) + 1)"),5411.03157939627) -> 5411.0316 | D25: =C25*B25 -> 5411.0316
A26: =IFERROR(__xludf.DUMMYFUNCTION("""COMPUTED_VALUE"""),"TRIPLE CHEESE BACON") -> TRIPLE CHEESE BACON | B26: =IFERROR(__xludf.DUMMYFUNCTION("""COMPUTED_VALUE"""),1) -> 1 | C26: =IFERROR(__xludf.DUMMYFUNCTION("INDEX(RECETAS!E:E, MAX(FILTER(ROW(RECETAS!A:A), RECETAS!A:A=A26)) + 1)"),6830.32040995182) -> 6830.3204 | D26: =C26*B26 -> 6830.3204
C27: =IFERROR(__xludf.DUMMYFUNCTION("INDEX(RECETAS!E:E, MAX(FILTER(ROW(RECETAS!A:A), RECETAS!A:A=A27)) + 1)"),"") | D27: =C27*B27 -> #VALUE!
C28: =IFERROR(__xludf.DUMMYFUNCTION("INDEX(RECETAS!E:E, MAX(FILTER(ROW(RECETAS!A:A), RECETAS!A:A=A28)) + 1)"),"") | D28: =C28*B28 -> #VALUE!
C29: =IFERROR(__xludf.DUMMYFUNCTION("INDEX(RECETAS!E:E, MAX(FILTER(ROW(RECETAS!A:A), RECETAS!A:A=A29)) + 1)"),"") | D29: =C29*B29 -> #VALUE!
C30: =IFERROR(__xludf.DUMMYFUNCTION("INDEX(RECETAS!E:E, MAX(FILTER(ROW(RECETAS!A:A), RECETAS!A:A=A30)) + 1)"),"") | D30: =C30*B30 -> #VALUE!
C31: =IFERROR(__xludf.DUMMYFUNCTION("INDEX(RECETAS!E:E, MAX(FILTER(ROW(RECETAS!A:A), RECETAS!A:A=A31)) + 1)"),"") | D31: =C31*B31 -> #VALUE!
C32: =IFERROR(__xludf.DUMMYFUNCTION("INDEX(RECETAS!E:E, MAX(FILTER(ROW(RECETAS!A:A), RECETAS!A:A=A32)) + 1)"),"") | D32: =C32*B32 -> #VALUE!
D34: =SUM(D4:D33) -> #VALUE! | E34: =E4+F4*1 -> 604300 | F34: =D34/E34 -> #VALUE!

Sheet CMV TOTAL 12-2025
A1: PRODUCTOS | B1: TOTAL | C1: COSTO UNITARIO | D1: COSTO TOTAL | E1: CMV | F1: CMV
A3: =IFERROR(__xludf.DUMMYFUNCTION("QUERY(ResumenVentas!A:B, ""Select A, sum(B) where A is not null group by A label sum(B) 'TOTAL'"", 1)"),"Producto") -> Producto | B3: =IFERROR(__xludf.DUMMYFUNCTION("""COMPUTED_VALUE"""),"TOTAL") -> TOTAL
A4: =IFERROR(__xludf.DUMMYFUNCTION("""COMPUTED_VALUE"""),"AGUA MANZANA H20") -> AGUA MANZANA H20 | B4: =IFERROR(__xludf.DUMMYFUNCTION("""COMPUTED_VALUE"""),9) -> 9 | C4: =IFERROR(__xludf.DUMMYFUNCTION("INDEX(RECETAS!E:E, MAX(FILTER(ROW(RECETAS!A:A), RECETAS!A:A=A4)) + 1)"),717.358333333333) -> 717.35833 | D4: =C4*B4 -> 6456.225 | E4: 7692710 | F4: 13670420
A5: =IFERROR(__xludf.DUMMYFUNCTION("""COMPUTED_VALUE"""),"AGUA MINERAL") -> AGUA MINERAL | B5: =IFERROR(__xludf.DUMMYFUNCTION("""COMPUTED_VALUE"""),45) -> 45 | C5: =IFERROR(__xludf.DUMMYFUNCTION("INDEX(RECETAS!E:E, MAX(FILTER(ROW(RECETAS!A:A), RECETAS!A:A=A5)) + 1)"),920.664166666666) -> 920.66417 | D5: =C5*B5 -> 41429.887
A6: =IFERROR(__xludf.DUMMYFUNCTION("""COMPUTED_VALUE"""),"AGUA POMELO H20") -> AGUA POMELO H20 | B6: =IFERROR(__xludf.DUMMYFUNCTION("""COMPUTED_VALUE"""),40) -> 40 | C6: =IFERROR(__xludf.DUMMYFUNCTION("INDEX(RECETAS!E:E, MAX(FILTER(ROW(RECETAS!A:A), RECETAS!A:A=A6)) + 1)"),717.375) -> 717.375 | D6: =C6*B6 -> 28695
A7: =IFERROR(__xludf.DUMMYFUNCTION("""COMPUTED_VALUE"""),"AMERICAN BURGER") -> AMERICAN BURGER | B7: =IFERROR(__xludf.DUMMYFUNCTION("""COMPUTED_VALUE"""),87) -> 87 | C7: =IFERROR(__xludf.DUMMYFUNCTION("INDEX(RECETAS!E:E, MAX(FILTER(ROW(RECETAS!A:A), RECETAS!A:A=A7)) + 1)"),5886.03157939627) -> 5886.0316 | D7: =C7*B7 -> 512084.75
A8: =IFERROR(__xludf.DUMMYFUNCTION("""COMPUTED_VALUE"""),"AROS DE CEBOLLA") -> AROS DE CEBOLLA | B8: =IFERROR(__xludf.DUMMYFUNCTION("""COMPUTED_VALUE"""),7) -> 7 | C8: =IFERROR(__xludf.DUMMYFUNCTION("INDEX(RECETAS!E:E, MAX(FILTER(ROW(RECETAS!A:A), RECETAS!A:A=A8)) + 1)"),2027.49327948717) -> 2027.4933 | D8: =C8*B8 -> 14192.453
A9: =IFERROR(__xludf.DUMMYFUNCTION("""COMPUTED_VALUE"""),"BLUE CHEESE") -> BLUE CHEESE | B9: =IFERROR(__xludf.DUMMYFUNCTION("""COMPUTED_VALUE"""),35) -> 35 | C9: =IFERROR(__xludf.DUMMYFUNCTION("INDEX(RECETAS!E:E, MAX(FILTER(ROW(RECETAS!A:A), RECETAS!A:A=A9)) + 1)"),5298.53157939627) -> 5298.5316 | D9: =C9*B9 -> 185448.61
A10: =IFERROR(__xludf.DUMMYFUNCTION("""COMPUTED_VALUE"""),"BOTELLA DE CERVEZA") -> BOTELLA DE CERVEZA | B10: =IFERROR(__xludf.DUMMYFUNCTION("""COMPUTED_VALUE"""),11) -> 11 | C10: =IFERROR(__xludf.DUMMYFUNCTION("INDEX(RECETAS!E:E, MAX(FILTER(ROW(RECETAS!A:A), RECETAS!A:A=A10)) + 1)"),1899.93933333333) -> 1899.9393 | D10: =C10*B10 -> 20899.333
A11: =IFERROR(__xludf.DUMMYFUNCTION("""COMPUTED_VALUE"""),"CHEESE BACON") -> CHEESE BACON | B11: =IFERROR(__xludf.DUMMYFUNCTION("""COMPUTED_VALUE"""),172) -> 172 | C11: =IFERROR(__xludf.DUMMYFUNCTION("INDEX(RECETAS!E:E, MAX(FILTER(ROW(RECETAS!A:A), RECETAS!A:A=A11)) + 1)"),5183.03047939627) -> 5183.0305 | D11: =C11*B11 -> 891481.24
A12: =IFERROR(__xludf.DUMMYFUNCTION("""COMPUTED_VALUE"""),"CHEESE BURGER") -> CHEESE BURGER | B12: =IFERROR(__xludf.DUMMYFUNCTION("""COMPUTED_VALUE"""),3) -> 3 | C12: =IFERROR(__xludf.DUMMYFUNCTION("INDEX(RECETAS!E:E, MAX(FILTER(ROW(RECETAS!A:A), RECETAS!A:A=A12)) + 1)"),5073.90657939627) -> 5073.9066 | D12: =C12*B12 -> 15221.72
A13: =IFERROR(__xludf.DUMMYFUNCTION("""COMPUTED_VALUE"""),"CHEESE BURGER CANJE") -> CHEESE BURGER CANJE | B13: =IFERROR(__xludf.DUMMYFUNCTION("""COMPUTED_VALUE"""),8) -> 8 | C13: =IFERROR(__xludf.DUMMYFUNCTION("INDEX(RECETAS!E:E, MAX(FILTER(ROW(RECETAS!A:A), RECETAS!A:A=A13)) + 1)"),2086.06704059829) -> 2086.067 | D13: =C13*B13 -> 16688.536
A14: =IFERROR(__xludf.DUMMYFUNCTION("""COMPUTED_VALUE"""),"CRISPY BURGER") -> CRISPY BURGER | B14: =IFERROR(__xludf.DUMMYFUNCTION("""COMPUTED_VALUE"""),51) -> 51 | C14: =IFERROR(__xludf.DUMMYFUNCTION("INDEX(RECETAS!E:E, MAX(FILTER(ROW(RECETAS!A:A), RECETAS!A:A=A14)) + 1)"),5233.03047939627) -> 5233.0305 | D14: =C14*B14 -> 266884.55
A15: =IFERROR(__xludf.DUMMYFUNCTION("""COMPUTED_VALUE"""),"DOBLE CUARTO") -> DOBLE CUARTO | B15: =IFERROR(__xludf.DUMMYFUNCTION("""COMPUTED_VALUE"""),50) -> 50 | C15: =IFERROR(__xludf.DUMMYFUNCTION("INDEX(RECETAS!E:E, MAX(FILTER(ROW(RECETAS!A:A), RECETAS!A:A=A15)) + 1)"),5326.66684303263) -> 5326.6668 | D15: =C15*B15 -> 266333.34
A16: =IFERROR(__xludf.DUMMYFUNCTION("""COMPUTED_VALUE"""),"EXTRA MEDALLON") -> EXTRA MEDALLON | B16: =IFERROR(__xludf.DUMMYFUNCTION("""COMPUTED_VALUE"""),3) -> 3 | C16: =IFERROR(__xludf.DUMMYFUNCTION("INDEX(RECETAS!E:E, MAX(FILTER(ROW(RECETAS!A:A), RECETAS!A:A=A16)) + 1)"),1421.75) -> 1421.75 | D16: =C16*B16 -> 4265.25
A17: =IFERROR(__xludf.DUMMYFUNCTION("""COMPUTED_VALUE"""),"HUMPTY BURGER") -> HUMPTY BURGER | B17: =IFERROR(__xludf.DUMMYFUNCTION("""COMPUTED_VALUE"""),74) -> 74 | C17: =IFERROR(__xludf.DUMMYFUNCTION("INDEX(RECETAS!E:E, MAX(FILTER(ROW(RECETAS!A:A), RECETAS!A:A=A17)) + 1)"),5409.69714606293) -> 5409.6971 | D17: =C17*B17 -> 400317.59
A18: =IFERROR(__xludf.DUMMYFUNCTION("""COMPUTED_VALUE"""),"JIMMY BURGER") -> JIMMY BURGER | B18: =IFERROR(__xludf.DUMMYFUNCTION("""COMPUTED_VALUE"""),34) -> 34 | C18: =IFERROR(__xludf.DUMMYFUNCTION("INDEX(RECETAS!E:E, MAX(FILTER(ROW(RECETAS!A:A), RECETAS!A:A=A18)) + 1)"),3923.49054884071) -> 3923.4905 | D18: =C18*B18 -> 133398.68
A19: =IFERROR(__xludf.DUMMYFUNCTION("""COMPUTED_VALUE"""),"MEDALLON VEGGIE") -> MEDALLON VEGGIE | B19: =IFERROR(__xludf.DUMMYFUNCTION("""COMPUTED_VALUE"""),1) -> 1 | C19: =IFERROR(__xludf.DUMMYFUNCTION("INDEX(RECETAS!E:E, MAX(FILTER(ROW(RECETAS!A:A), RECETAS!A:A=A19)) + 1)"),700) -> 700 | D19: =C19*B19 -> 700
A20: =IFERROR(__xludf.DUMMYFUNCTION("""COMPUTED_VALUE"""),"MEDIA PINTA DE CERVEZA") -> MEDIA PINTA DE CERVEZA | B20: =IFERROR(__xludf.DUMMYFUNCTION("""COMPUTED_VALUE"""),64) -> 64 | C20: =IFERROR(__xludf.DUMMYFUNCTION("INDEX(RECETAS!E:E, MAX(FILTER(ROW(RECETAS!A:A), RECETAS!A:A=A20)) + 1)"),949.969666666666) -> 949.96967 | D20: =C20*B20 -> 60798.059
A21: =IFERROR(__xludf.DUMMYFUNCTION("""COMPUTED_VALUE"""),"MIGI BURGER") -> MIGI BURGER | B21: =IFERROR(__xludf.DUMMYFUNCTION("""COMPUTED_VALUE"""),164) -> 164 | C21: =IFERROR(__xludf.DUMMYFUNCTION("INDEX(RECETAS!E:E, MAX(FILTER(ROW(RECETAS!A:A), RECETAS!A:A=A21)) + 1)"),4209.03157939627) -> 4209.0316 | D21: =C21*B21 -> 690281.18
A22: =IFERROR(__xludf.DUMMYFUNCTION("""COMPUTED_VALUE"""),"MIRINDA") -> MIRINDA | B22: =IFERROR(__xludf.DUMMYFUNCTION("""COMPUTED_VALUE"""),36) -> 36 | C22: =IFERROR(__xludf.DUMMYFUNCTION("INDEX(RECETAS!E:E, MAX(FILTER(ROW(RECETAS!A:A), RECETAS!A:A=A22)) + 1)"),758.113333333333) -> 758.11333 | D22: =C22*B22 -> 27292.08
A23: =IFERROR(__xludf.DUMMYFUNCTION("""COMPUTED_VALUE"""),"MOBY DICK") -> MOBY DICK | B23: =IFERROR(__xludf.DUMMYFUNCTION("""COMPUTED_VALUE"""),70) -> 70 | C23: =IFERROR(__xludf.DUMMYFUNCTION("INDEX(RECETAS!E:E, MAX(FILTER(ROW(RECETAS!A:A), RECETAS!A:A=A23)) + 1)"),8562.10924050738) -> 8562.1092 | D23: =C23*B23 -> 599347.65
A24: =IFERROR(__xludf.DUMMYFUNCTION("""COMPUTED_VALUE"""),"NUGGETS X 10") -> NUGGETS X 10 | B24: =IFERROR(__xludf.DUMMYFUNCTION("""COMPUTED_VALUE"""),12) -> 12 | C24: =IFERROR(__xludf.DUMMYFUNCTION("INDEX(RECETAS!E:E, MAX(FILTER(ROW(RECETAS!A:A), RECETAS!A:A=A24)) + 1)"),2756.21051282051) -> 2756.2105 | D24: =C24*B24 -> 33074.526
A25: =IFERROR(__xludf.DUMMYFUNCTION("""COMPUTED_VALUE"""),"NUGGETS X 6") -> NUGGETS X 6 | B25: =IFERROR(__xludf.DUMMYFUNCTION("""COMPUTED_VALUE"""),5) -> 5 | C25: =IFERROR(__xludf.DUMMYFUNCTION("INDEX(RECETAS!E:E, MAX(FILTER(ROW(RECETAS!A:A), RECETAS!A:A=A25)) + 1)"),1680.52117948717) -> 1680.5212 | D25: =C25*B25 -> 8402.6059
A26: =IFERROR(__xludf.DUMMYFUNCTION("""COMPUTED_VALUE"""),"ONION RINGS BURGER") -> ONION RINGS BURGER | B26: =IFERROR(__xludf.DUMMYFUNCTION("""COMPUTED_VALUE"""),26) -> 26 | C26: =IFERROR(__xludf.DUMMYFUNCTION("INDEX(RECETAS!E:E, MAX(FILTER(ROW(RECETAS!A:A), RECETAS!A:A=A26)) + 1)"),5660.1693127296) -> 5660.1693 | D26: =C26*B26 -> 147164.4
A27: =IFERROR(__xludf.DUMMYFUNCTION("""COMPUTED_VALUE"""),"PEPSI ") -> PEPSI | B27: =IFERROR(__xludf.DUMMYFUNCTION("""COMPUTED_VALUE"""),204) -> 204 | C27: =IFERROR(__xludf.DUMMYFUNCTION("INDEX(RECETAS!E:E, MAX(FILTER(ROW(RECETAS!A:A), RECETAS!A:A=A27)) + 1)"),770.53) -> 770.53 | D27: =C27*B27 -> 157188.12
A28: =IFERROR(__xludf.DUMMYFUNCTION("""COMPUTED_VALUE"""),"PEPSI BLACK") -> PEPSI BLACK | B28: =IFERROR(__xludf.DUMMYFUNCTION("""COMPUTED_VALUE"""),43) -> 43 | C28: =IFERROR(__xludf.DUMMYFUNCTION("INDEX(RECETAS!E:E, MAX(FILTER(ROW(RECETAS!A:A), RECETAS!A:A=A28)) + 1)"),758.1) -> 758.1 | D28: =C28*B28 -> 32598.3
A29: =IFERROR(__xludf.DUMMYFUNCTION("""COMPUTED_VALUE"""),"PINTA DE CERVEZA") -> PINTA DE CERVEZA | B29: =IFERROR(__xludf.DUMMYFUNCTION("""COMPUTED_VALUE"""),2) -> 2 | C29: =IFERROR(__xludf.DUMMYFUNCTION("INDEX(RECETAS!E:E, MAX(FILTER(ROW(RECETAS!A:A), RECETAS!A:A=A29)) + 1)"),1899.93933333333) -> 1899.9393 | D29: =C29*B29 -> 3799.8787
A30: =IFERROR(__xludf.DUMMYFUNCTION("""COMPUTED_VALUE"""),"PORCION DE PAPAS") -> PORCION DE PAPAS | B30: =IFERROR(__xludf.DUMMYFUNCTION("""COMPUTED_VALUE"""),19) -> 19 | C30: =IFERROR(__xludf.DUMMYFUNCTION("INDEX(RECETAS!E:E, MAX(FILTER(ROW(RECETAS!A:A), RECETAS!A:A=A30)) + 1)"),2292.92034615384) -> 2292.9203 | D30: =C30*B30 -> 43565.487
A31: =IFERROR(__xludf.DUMMYFUNCTION("""COMPUTED_VALUE"""),"PORCION DE PAPAS CON CHEDDAR Y BACON") -> PORCION DE PAPAS CON CHEDDAR Y BACON | B31: =IFERROR(__xludf.DUMMYFUNCTION("""COMPUTED_VALUE"""),6) -> 6 | C31: =IFERROR(__xludf.DUMMYFUNCTION("INDEX(RECETAS!E:E, MAX(FILTER(ROW(RECETAS!A:A), RECETAS!A:A=A31)) + 1)"),3229.7962032967) -> 3229.7962 | D31: =C31*B31 -> 19378.777
A32: =IFERROR(__xludf.DUMMYFUNCTION("""COMPUTED_VALUE"""),"PORCION DE PAPAS Y CHEDDAR") -> PORCION DE PAPAS Y CHEDDAR | B32: =IFERROR(__xludf.DUMMYFUNCTION("""COMPUTED_VALUE"""),7) -> 7 | C32: =IFERROR(__xludf.DUMMYFUNCTION("INDEX(RECETAS!E:E, MAX(FILTER(ROW(RECETAS!A:A), RECETAS!A:A=A32)) + 1)"),2948.1332032967) -> 2948.1332 | D32: =C32*B32 -> 20636.932
A33: =IFERROR(__xludf.DUMMYFUNCTION("""COMPUTED_VALUE"""),"POSTRE CHOCOTORTA") -> POSTRE CHOCOTORTA | B33: =IFERROR(__xludf.DUMMYFUNCTION("""COMPUTED_VALUE"""),13) -> 13 | C33: =IFERROR(__xludf.DUMMYFUNCTION("INDEX(RECETAS!E:E, MAX(FILTER(ROW(RECETAS!A:A), RECETAS!A:A=A33)) + 1)"),2800) -> 2800 | D33: =C33*B33 -> 36400
A34: =IFERROR(__xludf.DUMMYFUNCTION("""COMPUTED_VALUE"""),"POSTRE OREO") -> POSTRE OREO | B34: =IFERROR(__xludf.DUMMYFUNCTION("""COMPUTED_VALUE"""),12) -> 12 | C34: =IFERROR(__xludf.DUMMYFUNCTION("INDEX(RECETAS!E:E, MAX(FILTER(ROW(RECETAS!A:A), RECETAS!A:A=A34)) + 1)"),2800) -> 2800 | D34: =C34*B34 -> 33600
A35: =IFERROR(__xludf.DUMMYFUNCTION("""COMPUTED_VALUE"""),"PULLED PORK") -> PULLED PORK | B35: =IFERROR(__xludf.DUMMYFUNCTION("""COMPUTED_VALUE"""),63) -> 63 | C35: =IFERROR(__xludf.DUMMYFUNCTION("INDEX(RECETAS!E:E, MAX(FILTER(ROW(RECETAS!A:A), RECETAS!A:A=A35)) + 1)"),2652.60312106293) -> 2652.6031 | D35: =C35*B35 -> 167114
A36: =IFERROR(__xludf.DUMMYFUNCTION("""COMPUTED_VALUE"""),"SEVEN-UP") -> SEVEN-UP | B36: =IFERROR(__xludf.DUMMYFUNCTION("""COMPUTED_VALUE"""),126) -> 126 | C36: =IFERROR(__xludf.DUMMYFUNCTION("INDEX(RECETAS!E:E, MAX(FILTER(ROW(RECETAS!A:A), RECETAS!A:A=A36)) + 1)"),758.113333333333) -> 758.11333 | D36: =C36*B36 -> 95522.28
A37: =IFERROR(__xludf.DUMMYFUNCTION("""COMPUTED_VALUE"""),"SWEET BACON BURGER") -> SWEET BACON BURGER | B37: =IFERROR(__xludf.DUMMYFUNCTION("""COMPUTED_VALUE"""),31) -> 31 | C37: =IFERROR(__xludf.DUMMYFUNCTION("INDEX(RECETAS!E:E, MAX(FILTER(ROW(RECETAS!A:A), RECETAS!A:A=A37)) + 1)"),5148.53157939627) -> 5148.5316 | D37: =C37*B37 -> 159604.48
A38: =IFERROR(__xludf.DUMMYFUNCTION("""COMPUTED_VALUE"""),"SWEET ONION") -> SWEET ONION | B38: =IFERROR(__xludf.DUMMYFUNCTION("""COMPUTED_VALUE"""),68) -> 68 | C38: =IFERROR(__xludf.DUMMYFUNCTION("INDEX(RECETAS!E:E, MAX(FILTER(ROW(RECETAS!A:A), RECETAS!A:A=A38)) + 1)"),5183.03047939627) -> 5183.0305 | D38: =C38*B38 -> 352446.07
A39: =IFERROR(__xludf.DUMMYFUNCTION("""COMPUTED_VALUE"""),"TASTY WLB") -> TASTY WLB | B39: =IFERROR(__xludf.DUMMYFUNCTION("""COMPUTED_VALUE"""),41) -> 41 | C39: =IFERROR(__xludf.DUMMYFUNCTION("INDEX(RECETAS!E:E, MAX(FILTER(ROW(RECETAS!A:A), RECETAS!A:A=A39)) + 1)"),5411.03157939627) -> 5411.0316 | D39: =C39*B39 -> 221852.29
A40: =IFERROR(__xludf.DUMMYFUNCTION("""COMPUTED_VALUE"""),"TRIPLE CHEESE BACON") -> TRIPLE CHEESE BACON | B40: =IFERROR(__xludf.DUMMYFUNCTION("""COMPUTED_VALUE"""),64) -> 64 | C40: =IFERROR(__xludf.DUMMYFUNCTION("INDEX(RECETAS!E:E, MAX(FILTER(ROW(RECETAS!A:A), RECETAS!A:A=A40)) + 1)"),6830.32040995182) -> 6830.3204 | D40: =C40*B40 -> 437140.51
A41: =IFERROR(__xludf.DUMMYFUNCTION("""COMPUTED_VALUE"""),"VEGGIE BURGER") -> VEGGIE BURGER | B41: =IFERROR(__xludf.DUMMYFUNCTION("""COMPUTED_VALUE"""),26) -> 26 | C41: =IFERROR(__xludf.DUMMYFUNCTION("INDEX(RECETAS!E:E, MAX(FILTER(ROW(RECETAS!A:A), RECETAS!A:A=A41)) + 1)"),2674.4117877296) -> 2674.4118 | D41: =C41*B41 -> 69534.706
C43: =SUM(Tabla_2[COSTO UNITARIO]) -> 122558.62 | D43: =SUM(D4:D42) -> 6221239.5 | E43: $21,363,130.00 | F43: 38.62%

Sheet CMV TOTAL 01-2026
A1: PRODUCTOS | B1: TOTAL | C1: COSTO UNITARIO | D1: COSTO TOTAL | E1: CMV | F1: CMV
A3: =IFERROR(__xludf.DUMMYFUNCTION("QUERY(ResumenVentas!A:B, ""Select A, sum(B) where A is not null group by A label sum(B) 'TOTAL'"", 1)"),"Producto") -> Producto | B3: =IFERROR(__xludf.DUMMYFUNCTION("""COMPUTED_VALUE"""),"TOTAL") -> TOTAL
A4: =IFERROR(__xludf.DUMMYFUNCTION("""COMPUTED_VALUE"""),"AGUA MANZANA H20") -> AGUA MANZANA H20 | B4: =IFERROR(__xludf.DUMMYFUNCTION("""COMPUTED_VALUE"""),9) -> 9 | C4: =IFERROR(__xludf.DUMMYFUNCTION("INDEX(RECETAS!E:E, MAX(FILTER(ROW(RECETAS!A:A), RECETAS!A:A=A4)) + 1)"),717.358333333333) -> 717.35833 | D4: =C4*B4 -> 6456.225 | E4: =#REF! -> #REF! | F4: =#REF! -> #REF!
A5: =IFERROR(__xludf.DUMMYFUNCTION("""COMPUTED_VALUE"""),"AGUA MINERAL") -> AGUA MINERAL | B5: =IFERROR(__xludf.DUMMYFUNCTION("""COMPUTED_VALUE"""),45) -> 45 | C5: =IFERROR(__xludf.DUMMYFUNCTION("INDEX(RECETAS!E:E, MAX(FILTER(ROW(RECETAS!A:A), RECETAS!A:A=A5)) + 1)"),920.664166666666) -> 920.66417 | D5: =C5*B5 -> 41429.887
A6: =IFERROR(__xludf.DUMMYFUNCTION("""COMPUTED_VALUE"""),"AGUA POMELO H20") -> AGUA POMELO H20 | B6: =IFERROR(__xludf.DUMMYFUNCTION("""COMPUTED_VALUE"""),40) -> 40 | C6: =IFERROR(__xludf.DUMMYFUNCTION("INDEX(RECETAS!E:E, MAX(FILTER(ROW(RECETAS!A:A), RECETAS!A:A=A6)) + 1)"),717.375) -> 717.375 | D6: =C6*B6 -> 28695
A7: =IFERROR(__xludf.DUMMYFUNCTION("""COMPUTED_VALUE"""),"AMERICAN BURGER") -> AMERICAN BURGER | B7: =IFERROR(__xludf.DUMMYFUNCTION("""COMPUTED_VALUE"""),87) -> 87 | C7: =IFERROR(__xludf.DUMMYFUNCTION("INDEX(RECETAS!E:E, MAX(FILTER(ROW(RECETAS!A:A), RECETAS!A:A=A7)) + 1)"),5886.03157939627) -> 5886.0316 | D7: =C7*B7 -> 512084.75
A8: =IFERROR(__xludf.DUMMYFUNCTION("""COMPUTED_VALUE"""),"AROS DE CEBOLLA") -> AROS DE CEBOLLA | B8: =IFERROR(__xludf.DUMMYFUNCTION("""COMPUTED_VALUE"""),7) -> 7 | C8: =IFERROR(__xludf.DUMMYFUNCTION("INDEX(RECETAS!E:E, MAX(FILTER(ROW(RECETAS!A:A), RECETAS!A:A=A8)) + 1)"),2027.49327948717) -> 2027.4933 | D8: =C8*B8 -> 14192.453
A9: =IFERROR(__xludf.DUMMYFUNCTION("""COMPUTED_VALUE"""),"BLUE CHEESE") -> BLUE CHEESE | B9: =IFERROR(__xludf.DUMMYFUNCTION("""COMPUTED_VALUE"""),35) -> 35 | C9: =IFERROR(__xludf.DUMMYFUNCTION("INDEX(RECETAS!E:E, MAX(FILTER(ROW(RECETAS!A:A), RECETAS!A:A=A9)) + 1)"),5298.53157939627) -> 5298.5316 | D9: =C9*B9 -> 185448.61
A10: =IFERROR(__xludf.DUMMYFUNCTION("""COMPUTED_VALUE"""),"BOTELLA DE CERVEZA") -> BOTELLA DE CERVEZA | B10: =IFERROR(__xludf.DUMMYFUNCTION("""COMPUTED_VALUE"""),11) -> 11 | C10: =IFERROR(__xludf.DUMMYFUNCTION("INDEX(RECETAS!E:E, MAX(FILTER(ROW(RECETAS!A:A), RECETAS!A:A=A10)) + 1)"),1899.93933333333) -> 1899.9393 | D10: =C10*B10 -> 20899.333
A11: =IFERROR(__xludf.DUMMYFUNCTION("""COMPUTED_VALUE"""),"CHEESE BACON") -> CHEESE BACON | B11: =IFERROR(__xludf.DUMMYFUNCTION("""COMPUTED_VALUE"""),172) -> 172 | C11: =IFERROR(__xludf.DUMMYFUNCTION("INDEX(RECETAS!E:E, MAX(FILTER(ROW(RECETAS!A:A), RECETAS!A:A=A11)) + 1)"),5183.03047939627) -> 5183.0305 | D11: =C11*B11 -> 891481.24
A12: =IFERROR(__xludf.DUMMYFUNCTION("""COMPUTED_VALUE"""),"CHEESE BURGER") -> CHEESE BURGER | B12: =IFERROR(__xludf.DUMMYFUNCTION("""COMPUTED_VALUE"""),3) -> 3 | C12: =IFERROR(__xludf.DUMMYFUNCTION("INDEX(RECETAS!E:E, MAX(FILTER(ROW(RECETAS!A:A), RECETAS!A:A=A12)) + 1)"),5073.90657939627) -> 5073.9066 | D12: =C12*B12 -> 15221.72
A13: =IFERROR(__xludf.DUMMYFUNCTION("""COMPUTED_VALUE"""),"CHEESE BURGER CANJE") -> CHEESE BURGER CANJE | B13: =IFERROR(__xludf.DUMMYFUNCTION("""COMPUTED_VALUE"""),8) -> 8 | C13: =IFERROR(__xludf.DUMMYFUNCTION("INDEX(RECETAS!E:E, MAX(FILTER(ROW(RECETAS!A:A), RECETAS!A:A=A13)) + 1)"),2086.06704059829) -> 2086.067 | D13: =C13*B13 -> 16688.536
A14: =IFERROR(__xludf.DUMMYFUNCTION("""COMPUTED_VALUE"""),"CRISPY BURGER") -> CRISPY BURGER | B14: =IFERROR(__xludf.DUMMYFUNCTION("""COMPUTED_VALUE"""),51) -> 51 | C14: =IFERROR(__xludf.DUMMYFUNCTION("INDEX(RECETAS!E:E, MAX(FILTER(ROW(RECETAS!A:A), RECETAS!A:A=A14)) + 1)"),5233.03047939627) -> 5233.0305 | D14: =C14*B14 -> 266884.55
A15: =IFERROR(__xludf.DUMMYFUNCTION("""COMPUTED_VALUE"""),"DOBLE CUARTO") -> DOBLE CUARTO | B15: =IFERROR(__xludf.DUMMYFUNCTION("""COMPUTED_VALUE"""),50) -> 50 | C15: =IFERROR(__xludf.DUMMYFUNCTION("INDEX(RECETAS!E:E, MAX(FILTER(ROW(RECETAS!A:A), RECETAS!A:A=A15)) + 1)"),5326.66684303263) -> 5326.6668 | D15: =C15*B15 -> 266333.34
A16: =IFERROR(__xludf.DUMMYFUNCTION("""COMPUTED_VALUE"""),"EXTRA MEDALLON") -> EXTRA MEDALLON | B16: =IFERROR(__xludf.DUMMYFUNCTION("""COMPUTED_VALUE"""),3) -> 3 | C16: =IFERROR(__xludf.DUMMYFUNCTION("INDEX(RECETAS!E:E, MAX(FILTER(ROW(RECETAS!A:A), RECETAS!A:A=A16)) + 1)"),1421.75) -> 1421.75 | D16: =C16*B16 -> 4265.25
A17: =IFERROR(__xludf.DUMMYFUNCTION("""COMPUTED_VALUE"""),"HUMPTY BURGER") -> HUMPTY BURGER | B17: =IFERROR(__xludf.DUMMYFUNCTION("""COMPUTED_VALUE"""),74) -> 74 | C17: =IFERROR(__xludf.DUMMYFUNCTION("INDEX(RECETAS!E:E, MAX(FILTER(ROW(RECETAS!A:A), RECETAS!A:A=A17)) + 1)"),5409.69714606293) -> 5409.6971 | D17: =C17*B17 -> 400317.59
A18: =IFERROR(__xludf.DUMMYFUNCTION("""COMPUTED_VALUE"""),"JIMMY BURGER") -> JIMMY BURGER | B18: =IFERROR(__xludf.DUMMYFUNCTION("""COMPUTED_VALUE"""),34) -> 34 | C18: =IFERROR(__xludf.DUMMYFUNCTION("INDEX(RECETAS!E:E, MAX(FILTER(ROW(RECETAS!A:A), RECETAS!A:A=A18)) + 1)"),3923.49054884071) -> 3923.4905 | D18: =C18*B18 -> 133398.68
A19: =IFERROR(__xludf.DUMMYFUNCTION("""COMPUTED_VALUE"""),"MEDALLON VEGGIE") -> MEDALLON VEGGIE | B19: =IFERROR(__xludf.DUMMYFUNCTION("""COMPUTED_VALUE"""),1) -> 1 | C19: =IFERROR(__xludf.DUMMYFUNCTION("INDEX(RECETAS!E:E, MAX(FILTER(ROW(RECETAS!A:A), RECETAS!A:A=A19)) + 1)"),700) -> 700 | D19: =C19*B19 -> 700
A20: =IFERROR(__xludf.DUMMYFUNCTION("""COMPUTED_VALUE"""),"MEDIA PINTA DE CERVEZA") -> MEDIA PINTA DE CERVEZA | B20: =IFERROR(__xludf.DUMMYFUNCTION("""COMPUTED_VALUE"""),64) -> 64 | C20: =IFERROR(__xludf.DUMMYFUNCTION("INDEX(RECETAS!E:E, MAX(FILTER(ROW(RECETAS!A:A), RECETAS!A:A=A20)) + 1)"),949.969666666666) -> 949.96967 | D20: =C20*B20 -> 60798.059
A21: =IFERROR(__xludf.DUMMYFUNCTION("""COMPUTED_VALUE"""),"MIGI BURGER") -> MIGI BURGER | B21: =IFERROR(__xludf.DUMMYFUNCTION("""COMPUTED_VALUE"""),164) -> 164 | C21: =IFERROR(__xludf.DUMMYFUNCTION("INDEX(RECETAS!E:E, MAX(FILTER(ROW(RECETAS!A:A), RECETAS!A:A=A21)) + 1)"),4209.03157939627) -> 4209.0316 | D21: =C21*B21 -> 690281.18
A22: =IFERROR(__xludf.DUMMYFUNCTION("""COMPUTED_VALUE"""),"MIRINDA") -> MIRINDA | B22: =IFERROR(__xludf.DUMMYFUNCTION("""COMPUTED_VALUE"""),36) -> 36 | C22: =IFERROR(__xludf.DUMMYFUNCTION("INDEX(RECETAS!E:E, MAX(FILTER(ROW(RECETAS!A:A), RECETAS!A:A=A22)) + 1)"),758.113333333333) -> 758.11333 | D22: =C22*B22 -> 27292.08
A23: =IFERROR(__xludf.DUMMYFUNCTION("""COMPUTED_VALUE"""),"MOBY DICK") -> MOBY DICK | B23: =IFERROR(__xludf.DUMMYFUNCTION("""COMPUTED_VALUE"""),70) -> 70 | C23: =IFERROR(__xludf.DUMMYFUNCTION("INDEX(RECETAS!E:E, MAX(FILTER(ROW(RECETAS!A:A), RECETAS!A:A=A23)) + 1)"),8562.10924050738) -> 8562.1092 | D23: =C23*B23 -> 599347.65
A24: =IFERROR(__xludf.DUMMYFUNCTION("""COMPUTED_VALUE"""),"NUGGETS X 10") -> NUGGETS X 10 | B24: =IFERROR(__xludf.DUMMYFUNCTION("""COMPUTED_VALUE"""),12) -> 12 | C24: =IFERROR(__xludf.DUMMYFUNCTION("INDEX(RECETAS!E:E, MAX(FILTER(ROW(RECETAS!A:A), RECETAS!A:A=A24)) + 1)"),2756.21051282051) -> 2756.2105 | D24: =C24*B24 -> 33074.526
A25: =IFERROR(__xludf.DUMMYFUNCTION("""COMPUTED_VALUE"""),"NUGGETS X 6") -> NUGGETS X 6 | B25: =IFERROR(__xludf.DUMMYFUNCTION("""COMPUTED_VALUE"""),5) -> 5 | C25: =IFERROR(__xludf.DUMMYFUNCTION("INDEX(RECETAS!E:E, MAX(FILTER(ROW(RECETAS!A:A), RECETAS!A:A=A25)) + 1)"),1680.52117948717) -> 1680.5212 | D25: =C25*B25 -> 8402.6059
A26: =IFERROR(__xludf.DUMMYFUNCTION("""COMPUTED_VALUE"""),"ONION RINGS BURGER") -> ONION RINGS BURGER | B26: =IFERROR(__xludf.DUMMYFUNCTION("""COMPUTED_VALUE"""),26) -> 26 | C26: =IFERROR(__xludf.DUMMYFUNCTION("INDEX(RECETAS!E:E, MAX(FILTER(ROW(RECETAS!A:A), RECETAS!A:A=A26)) + 1)"),5660.1693127296) -> 5660.1693 | D26: =C26*B26 -> 147164.4
A27: =IFERROR(__xludf.DUMMYFUNCTION("""COMPUTED_VALUE"""),"PEPSI ") -> PEPSI | B27: =IFERROR(__xludf.DUMMYFUNCTION("""COMPUTED_VALUE"""),204) -> 204 | C27: =IFERROR(__xludf.DUMMYFUNCTION("INDEX(RECETAS!E:E, MAX(FILTER(ROW(RECETAS!A:A), RECETAS!A:A=A27)) + 1)"),770.53) -> 770.53 | D27: =C27*B27 -> 157188.12
A28: =IFERROR(__xludf.DUMMYFUNCTION("""COMPUTED_VALUE"""),"PEPSI BLACK") -> PEPSI BLACK | B28: =IFERROR(__xludf.DUMMYFUNCTION("""COMPUTED_VALUE"""),43) -> 43 | C28: =IFERROR(__xludf.DUMMYFUNCTION("INDEX(RECETAS!E:E, MAX(FILTER(ROW(RECETAS!A:A), RECETAS!A:A=A28)) + 1)"),758.1) -> 758.1 | D28: =C28*B28 -> 32598.3
A29: =IFERROR(__xludf.DUMMYFUNCTION("""COMPUTED_VALUE"""),"PINTA DE CERVEZA") -> PINTA DE CERVEZA | B29: =IFERROR(__xludf.DUMMYFUNCTION("""COMPUTED_VALUE"""),2) -> 2 | C29: =IFERROR(__xludf.DUMMYFUNCTION("INDEX(RECETAS!E:E, MAX(FILTER(ROW(RECETAS!A:A), RECETAS!A:A=A29)) + 1)"),1899.93933333333) -> 1899.9393 | D29: =C29*B29 -> 3799.8787
A30: =IFERROR(__xludf.DUMMYFUNCTION("""COMPUTED_VALUE"""),"PORCION DE PAPAS") -> PORCION DE PAPAS | B30: =IFERROR(__xludf.DUMMYFUNCTION("""COMPUTED_VALUE"""),19) -> 19 | C30: =IFERROR(__xludf.DUMMYFUNCTION("INDEX(RECETAS!E:E, MAX(FILTER(ROW(RECETAS!A:A), RECETAS!A:A=A30)) + 1)"),2292.92034615384) -> 2292.9203 | D30: =C30*B30 -> 43565.487
A31: =IFERROR(__xludf.DUMMYFUNCTION("""COMPUTED_VALUE"""),"PORCION DE PAPAS CON CHEDDAR Y BACON") -> PORCION DE PAPAS CON CHEDDAR Y BACON | B31: =IFERROR(__xludf.DUMMYFUNCTION("""COMPUTED_VALUE"""),6) -> 6 | C31: =IFERROR(__xludf.DUMMYFUNCTION("INDEX(RECETAS!E:E, MAX(FILTER(ROW(RECETAS!A:A), RECETAS!A:A=A31)) + 1)"),3229.7962032967) -> 3229.7962 | D31: =C31*B31 -> 19378.777
A32: =IFERROR(__xludf.DUMMYFUNCTION("""COMPUTED_VALUE"""),"PORCION DE PAPAS Y CHEDDAR") -> PORCION DE PAPAS Y CHEDDAR | B32: =IFERROR(__xludf.DUMMYFUNCTION("""COMPUTED_VALUE"""),7) -> 7 | C32: =IFERROR(__xludf.DUMMYFUNCTION("INDEX(RECETAS!E:E, MAX(FILTER(ROW(RECETAS!A:A), RECETAS!A:A=A32)) + 1)"),2948.1332032967) -> 2948.1332 | D32: =C32*B32 -> 20636.932
A33: =IFERROR(__xludf.DUMMYFUNCTION("""COMPUTED_VALUE"""),"POSTRE CHOCOTORTA") -> POSTRE CHOCOTORTA | B33: =IFERROR(__xludf.DUMMYFUNCTION("""COMPUTED_VALUE"""),13) -> 13 | C33: =IFERROR(__xludf.DUMMYFUNCTION("INDEX(RECETAS!E:E, MAX(FILTER(ROW(RECETAS!A:A), RECETAS!A:A=A33)) + 1)"),2800) -> 2800 | D33: =C33*B33 -> 36400
A34: =IFERROR(__xludf.DUMMYFUNCTION("""COMPUTED_VALUE"""),"POSTRE OREO") -> POSTRE OREO | B34: =IFERROR(__xludf.DUMMYFUNCTION("""COMPUTED_VALUE"""),12) -> 12 | C34: =IFERROR(__xludf.DUMMYFUNCTION("INDEX(RECETAS!E:E, MAX(FILTER(ROW(RECETAS!A:A), RECETAS!A:A=A34)) + 1)"),2800) -> 2800 | D34: =C34*B34 -> 33600
A35: =IFERROR(__xludf.DUMMYFUNCTION("""COMPUTED_VALUE"""),"PULLED PORK") -> PULLED PORK | B35: =IFERROR(__xludf.DUMMYFUNCTION("""COMPUTED_VALUE"""),63) -> 63 | C35: =IFERROR(__xludf.DUMMYFUNCTION("INDEX(RECETAS!E:E, MAX(FILTER(ROW(RECETAS!A:A), RECETAS!A:A=A35)) + 1)"),2652.60312106293) -> 2652.6031 | D35: =C35*B35 -> 167114
A36: =IFERROR(__xludf.DUMMYFUNCTION("""COMPUTED_VALUE"""),"SEVEN-UP") -> SEVEN-UP | B36: =IFERROR(__xludf.DUMMYFUNCTION("""COMPUTED_VALUE"""),126) -> 126 | C36: =IFERROR(__xludf.DUMMYFUNCTION("INDEX(RECETAS!E:E, MAX(FILTER(ROW(RECETAS!A:A), RECETAS!A:A=A36)) + 1)"),758.113333333333) -> 758.11333 | D36: =C36*B36 -> 95522.28
A37: =IFERROR(__xludf.DUMMYFUNCTION("""COMPUTED_VALUE"""),"SWEET BACON BURGER") -> SWEET BACON BURGER | B37: =IFERROR(__xludf.DUMMYFUNCTION("""COMPUTED_VALUE"""),31) -> 31 | C37: =IFERROR(__xludf.DUMMYFUNCTION("INDEX(RECETAS!E:E, MAX(FILTER(ROW(RECETAS!A:A), RECETAS!A:A=A37)) + 1)"),5148.53157939627) -> 5148.5316 | D37: =C37*B37 -> 159604.48
A38: =IFERROR(__xludf.DUMMYFUNCTION("""COMPUTED_VALUE"""),"SWEET ONION") -> SWEET ONION | B38: =IFERROR(__xludf.DUMMYFUNCTION("""COMPUTED_VALUE"""),68) -> 68 | C38: =IFERROR(__xludf.DUMMYFUNCTION("INDEX(RECETAS!E:E, MAX(FILTER(ROW(RECETAS!A:A), RECETAS!A:A=A38)) + 1)"),5183.03047939627) -> 5183.0305 | D38: =C38*B38 -> 352446.07
A39: =IFERROR(__xludf.DUMMYFUNCTION("""COMPUTED_VALUE"""),"TASTY WLB") -> TASTY WLB | B39: =IFERROR(__xludf.DUMMYFUNCTION("""COMPUTED_VALUE"""),41) -> 41 | C39: =IFERROR(__xludf.DUMMYFUNCTION("INDEX(RECETAS!E:E, MAX(FILTER(ROW(RECETAS!A:A), RECETAS!A:A=A39)) + 1)"),5411.03157939627) -> 5411.0316 | D39: =C39*B39 -> 221852.29
A40: =IFERROR(__xludf.DUMMYFUNCTION("""COMPUTED_VALUE"""),"TRIPLE CHEESE BACON") -> TRIPLE CHEESE BACON | B40: =IFERROR(__xludf.DUMMYFUNCTION("""COMPUTED_VALUE"""),64) -> 64 | C40: =IFERROR(__xludf.DUMMYFUNCTION("INDEX(RECETAS!E:E, MAX(FILTER(ROW(RECETAS!A:A), RECETAS!A:A=A40)) + 1)"),6830.32040995182) -> 6830.3204 | D40: =C40*B40 -> 437140.51
A41: =IFERROR(__xludf.DUMMYFUNCTION("""COMPUTED_VALUE"""),"VEGGIE BURGER") -> VEGGIE BURGER | B41: =IFERROR(__xludf.DUMMYFUNCTION("""COMPUTED_VALUE"""),26) -> 26 | C41: =IFERROR(__xludf.DUMMYFUNCTION("INDEX(RECETAS!E:E, MAX(FILTER(ROW(RECETAS!A:A), RECETAS!A:A=A41)) + 1)"),2674.4117877296) -> 2674.4118 | D41: =C41*B41 -> 69534.706
C42: =IFERROR(__xludf.DUMMYFUNCTION("INDEX(RECETAS!E:E, MAX(FILTER(ROW(RECETAS!A:A), RECETAS!A:A=A42)) + 1)"),"") | D42: =C42*B42 -> #VALUE!
C43: =SUM(Tabla_3[COSTO UNITARIO]) -> 122558.62 | D43: =SUM(D4:D42) -> #VALUE! | E43: =E4+F4 -> #REF! | F43: =D43/E43 -> #VALUE!

Sheet CMV TOTAL 02-2026
A1: PRODUCTOS | B1: TOTAL | C1: COSTO UNITARIO | D1: COSTO TOTAL | E1: CMV | F1: CMV
A3: =IFERROR(__xludf.DUMMYFUNCTION("QUERY(ResumenVentas!A:B, ""Select A, sum(B) where A is not null group by A label sum(B) 'TOTAL'"", 1)"),"Producto") -> Producto | B3: =IFERROR(__xludf.DUMMYFUNCTION("""COMPUTED_VALUE"""),"TOTAL") -> TOTAL
A4: =IFERROR(__xludf.DUMMYFUNCTION("""COMPUTED_VALUE"""),"AGUA MANZANA H20") -> AGUA MANZANA H20 | B4: =IFERROR(__xludf.DUMMYFUNCTION("""COMPUTED_VALUE"""),9) -> 9 | C4: =IFERROR(__xludf.DUMMYFUNCTION("INDEX(RECETAS!E:E, MAX(FILTER(ROW(RECETAS!A:A), RECETAS!A:A=A4)) + 1)"),717.358333333333) -> 717.35833 | D4: =C4*B4 -> 6456.225 | E4: =#REF! -> #REF! | F4: =#REF! -> #REF!
A5: =IFERROR(__xludf.DUMMYFUNCTION("""COMPUTED_VALUE"""),"AGUA MINERAL") -> AGUA MINERAL | B5: =IFERROR(__xludf.DUMMYFUNCTION("""COMPUTED_VALUE"""),45) -> 45 | C5: =IFERROR(__xludf.DUMMYFUNCTION("INDEX(RECETAS!E:E, MAX(FILTER(ROW(RECETAS!A:A), RECETAS!A:A=A5)) + 1)"),920.664166666666) -> 920.66417 | D5: =C5*B5 -> 41429.887
A6: =IFERROR(__xludf.DUMMYFUNCTION("""COMPUTED_VALUE"""),"AGUA POMELO H20") -> AGUA POMELO H20 | B6: =IFERROR(__xludf.DUMMYFUNCTION("""COMPUTED_VALUE"""),40) -> 40 | C6: =IFERROR(__xludf.DUMMYFUNCTION("INDEX(RECETAS!E:E, MAX(FILTER(ROW(RECETAS!A:A), RECETAS!A:A=A6)) + 1)"),717.375) -> 717.375 | D6: =C6*B6 -> 28695
A7: =IFERROR(__xludf.DUMMYFUNCTION("""COMPUTED_VALUE"""),"AMERICAN BURGER") -> AMERICAN BURGER | B7: =IFERROR(__xludf.DUMMYFUNCTION("""COMPUTED_VALUE"""),87) -> 87 | C7: =IFERROR(__xludf.DUMMYFUNCTION("INDEX(RECETAS!E:E, MAX(FILTER(ROW(RECETAS!A:A), RECETAS!A:A=A7)) + 1)"),5886.03157939627) -> 5886.0316 | D7: =C7*B7 -> 512084.75
A8: =IFERROR(__xludf.DUMMYFUNCTION("""COMPUTED_VALUE"""),"AROS DE CEBOLLA") -> AROS DE CEBOLLA | B8: =IFERROR(__xludf.DUMMYFUNCTION("""COMPUTED_VALUE"""),7) -> 7 | C8: =IFERROR(__xludf.DUMMYFUNCTION("INDEX(RECETAS!E:E, MAX(FILTER(ROW(RECETAS!A:A), RECETAS!A:A=A8)) + 1)"),2027.49327948717) -> 2027.4933 | D8: =C8*B8 -> 14192.453
A9: =IFERROR(__xludf.DUMMYFUNCTION("""COMPUTED_VALUE"""),"BLUE CHEESE") -> BLUE CHEESE | B9: =IFERROR(__xludf.DUMMYFUNCTION("""COMPUTED_VALUE"""),35) -> 35 | C9: =IFERROR(__xludf.DUMMYFUNCTION("INDEX(RECETAS!E:E, MAX(FILTER(ROW(RECETAS!A:A), RECETAS!A:A=A9)) + 1)"),5298.53157939627) -> 5298.5316 | D9: =C9*B9 -> 185448.61
A10: =IFERROR(__xludf.DUMMYFUNCTION("""COMPUTED_VALUE"""),"BOTELLA DE CERVEZA") -> BOTELLA DE CERVEZA | B10: =IFERROR(__xludf.DUMMYFUNCTION("""COMPUTED_VALUE"""),11) -> 11 | C10: =IFERROR(__xludf.DUMMYFUNCTION("INDEX(RECETAS!E:E, MAX(FILTER(ROW(RECETAS!A:A), RECETAS!A:A=A10)) + 1)"),1899.93933333333) -> 1899.9393 | D10: =C10*B10 -> 20899.333
A11: =IFERROR(__xludf.DUMMYFUNCTION("""COMPUTED_VALUE"""),"CHEESE BACON") -> CHEESE BACON | B11: =IFERROR(__xludf.DUMMYFUNCTION("""COMPUTED_VALUE"""),172) -> 172 | C11: =IFERROR(__xludf.DUMMYFUNCTION("INDEX(RECETAS!E:E, MAX(FILTER(ROW(RECETAS!A:A), RECETAS!A:A=A11)) + 1)"),5183.03047939627) -> 5183.0305 | D11: =C11*B11 -> 891481.24
A12: =IFERROR(__xludf.DUMMYFUNCTION("""COMPUTED_VALUE"""),"CHEESE BURGER") -> CHEESE BURGER | B12: =IFERROR(__xludf.DUMMYFUNCTION("""COMPUTED_VALUE"""),3) -> 3 | C12: =IFERROR(__xludf.DUMMYFUNCTION("INDEX(RECETAS!E:E, MAX(FILTER(ROW(RECETAS!A:A), RECETAS!A:A=A12)) + 1)"),5073.90657939627) -> 5073.9066 | D12: =C12*B12 -> 15221.72
A13: =IFERROR(__xludf.DUMMYFUNCTION("""COMPUTED_VALUE"""),"CHEESE BURGER CANJE") -> CHEESE BURGER CANJE | B13: =IFERROR(__xludf.DUMMYFUNCTION("""COMPUTED_VALUE"""),8) -> 8 | C13: =IFERROR(__xludf.DUMMYFUNCTION("INDEX(RECETAS!E:E, MAX(FILTER(ROW(RECETAS!A:A), RECETAS!A:A=A13)) + 1)"),2086.06704059829) -> 2086.067 | D13: =C13*B13 -> 16688.536
A14: =IFERROR(__xludf.DUMMYFUNCTION("""COMPUTED_VALUE"""),"CRISPY BURGER") -> CRISPY BURGER | B14: =IFERROR(__xludf.DUMMYFUNCTION("""COMPUTED_VALUE"""),51) -> 51 | C14: =IFERROR(__xludf.DUMMYFUNCTION("INDEX(RECETAS!E:E, MAX(FILTER(ROW(RECETAS!A:A), RECETAS!A:A=A14)) + 1)"),5233.03047939627) -> 5233.0305 | D14: =C14*B14 -> 266884.55
A15: =IFERROR(__xludf.DUMMYFUNCTION("""COMPUTED_VALUE"""),"DOBLE CUARTO") -> DOBLE CUARTO | B15: =IFERROR(__xludf.DUMMYFUNCTION("""COMPUTED_VALUE"""),50) -> 50 | C15: =IFERROR(__xludf.DUMMYFUNCTION("INDEX(RECETAS!E:E, MAX(FILTER(ROW(RECETAS!A:A), RECETAS!A:A=A15)) + 1)"),5326.66684303263) -> 5326.6668 | D15: =C15*B15 -> 266333.34
A16: =IFERROR(__xludf.DUMMYFUNCTION("""COMPUTED_VALUE"""),"EXTRA MEDALLON") -> EXTRA MEDALLON | B16: =IFERROR(__xludf.DUMMYFUNCTION("""COMPUTED_VALUE"""),3) -> 3 | C16: =IFERROR(__xludf.DUMMYFUNCTION("INDEX(RECETAS!E:E, MAX(FILTER(ROW(RECETAS!A:A), RECETAS!A:A=A16)) + 1)"),1421.75) -> 1421.75 | D16: =C16*B16 -> 4265.25
A17: =IFERROR(__xludf.DUMMYFUNCTION("""COMPUTED_VALUE"""),"HUMPTY BURGER") -> HUMPTY BURGER | B17: =IFERROR(__xludf.DUMMYFUNCTION("""COMPUTED_VALUE"""),74) -> 74 | C17: =IFERROR(__xludf.DUMMYFUNCTION("INDEX(RECETAS!E:E, MAX(FILTER(ROW(RECETAS!A:A), RECETAS!A:A=A17)) + 1)"),5409.69714606293) -> 5409.6971 | D17: =C17*B17 -> 400317.59
A18: =IFERROR(__xludf.DUMMYFUNCTION("""COMPUTED_VALUE"""),"JIMMY BURGER") -> JIMMY BURGER | B18: =IFERROR(__xludf.DUMMYFUNCTION("""COMPUTED_VALUE"""),34) -> 34 | C18: =IFERROR(__xludf.DUMMYFUNCTION("INDEX(RECETAS!E:E, MAX(FILTER(ROW(RECETAS!A:A), RECETAS!A:A=A18)) + 1)"),3923.49054884071) -> 3923.4905 | D18: =C18*B18 -> 133398.68
A19: =IFERROR(__xludf.DUMMYFUNCTION("""COMPUTED_VALUE"""),"MEDALLON VEGGIE") -> MEDALLON VEGGIE | B19: =IFERROR(__xludf.DUMMYFUNCTION("""COMPUTED_VALUE"""),1) -> 1 | C19: =IFERROR(__xludf.DUMMYFUNCTION("INDEX(RECETAS!E:E, MAX(FILTER(ROW(RECETAS!A:A), RECETAS!A:A=A19)) + 1)"),700) -> 700 | D19: =C19*B19 -> 700
A20: =IFERROR(__xludf.DUMMYFUNCTION("""COMPUTED_VALUE"""),"MEDIA PINTA DE CERVEZA") -> MEDIA PINTA DE CERVEZA | B20: =IFERROR(__xludf.DUMMYFUNCTION("""COMPUTED_VALUE"""),64) -> 64 | C20: =IFERROR(__xludf.DUMMYFUNCTION("INDEX(RECETAS!E:E, MAX(FILTER(ROW(RECETAS!A:A), RECETAS!A:A=A20)) + 1)"),949.969666666666) -> 949.96967 | D20: =C20*B20 -> 60798.059
A21: =IFERROR(__xludf.DUMMYFUNCTION("""COMPUTED_VALUE"""),"MIGI BURGER") -> MIGI BURGER | B21: =IFERROR(__xludf.DUMMYFUNCTION("""COMPUTED_VALUE"""),164) -> 164 | C21: =IFERROR(__xludf.DUMMYFUNCTION("INDEX(RECETAS!E:E, MAX(FILTER(ROW(RECETAS!A:A), RECETAS!A:A=A21)) + 1)"),4209.03157939627) -> 4209.0316 | D21: =C21*B21 -> 690281.18
A22: =IFERROR(__xludf.DUMMYFUNCTION("""COMPUTED_VALUE"""),"MIRINDA") -> MIRINDA | B22: =IFERROR(__xludf.DUMMYFUNCTION("""COMPUTED_VALUE"""),36) -> 36 | C22: =IFERROR(__xludf.DUMMYFUNCTION("INDEX(RECETAS!E:E, MAX(FILTER(ROW(RECETAS!A:A), RECETAS!A:A=A22)) + 1)"),758.113333333333) -> 758.11333 | D22: =C22*B22 -> 27292.08
A23: =IFERROR(__xludf.DUMMYFUNCTION("""COMPUTED_VALUE"""),"MOBY DICK") -> MOBY DICK | B23: =IFERROR(__xludf.DUMMYFUNCTION("""COMPUTED_VALUE"""),70) -> 70 | C23: =IFERROR(__xludf.DUMMYFUNCTION("INDEX(RECETAS!E:E, MAX(FILTER(ROW(RECETAS!A:A), RECETAS!A:A=A23)) + 1)"),8562.10924050738) -> 8562.1092 | D23: =C23*B23 -> 599347.65
A24: =IFERROR(__xludf.DUMMYFUNCTION("""COMPUTED_VALUE"""),"NUGGETS X 10") -> NUGGETS X 10 | B24: =IFERROR(__xludf.DUMMYFUNCTION("""COMPUTED_VALUE"""),12) -> 12 | C24: =IFERROR(__xludf.DUMMYFUNCTION("INDEX(RECETAS!E:E, MAX(FILTER(ROW(RECETAS!A:A), RECETAS!A:A=A24)) + 1)"),2756.21051282051) -> 2756.2105 | D24: =C24*B24 -> 33074.526
A25: =IFERROR(__xludf.DUMMYFUNCTION("""COMPUTED_VALUE"""),"NUGGETS X 6") -> NUGGETS X 6 | B25: =IFERROR(__xludf.DUMMYFUNCTION("""COMPUTED_VALUE"""),5) -> 5 | C25: =IFERROR(__xludf.DUMMYFUNCTION("INDEX(RECETAS!E:E, MAX(FILTER(ROW(RECETAS!A:A), RECETAS!A:A=A25)) + 1)"),1680.52117948717) -> 1680.5212 | D25: =C25*B25 -> 8402.6059
A26: =IFERROR(__xludf.DUMMYFUNCTION("""COMPUTED_VALUE"""),"ONION RINGS BURGER") -> ONION RINGS BURGER | B26: =IFERROR(__xludf.DUMMYFUNCTION("""COMPUTED_VALUE"""),26) -> 26 | C26: =IFERROR(__xludf.DUMMYFUNCTION("INDEX(RECETAS!E:E, MAX(FILTER(ROW(RECETAS!A:A), RECETAS!A:A=A26)) + 1)"),5660.1693127296) -> 5660.1693 | D26: =C26*B26 -> 147164.4
A27: =IFERROR(__xludf.DUMMYFUNCTION("""COMPUTED_VALUE"""),"PEPSI ") -> PEPSI | B27: =IFERROR(__xludf.DUMMYFUNCTION("""COMPUTED_VALUE"""),204) -> 204 | C27: =IFERROR(__xludf.DUMMYFUNCTION("INDEX(RECETAS!E:E, MAX(FILTER(ROW(RECETAS!A:A), RECETAS!A:A=A27)) + 1)"),770.53) -> 770.53 | D27: =C27*B27 -> 157188.12
A28: =IFERROR(__xludf.DUMMYFUNCTION("""COMPUTED_VALUE"""),"PEPSI BLACK") -> PEPSI BLACK | B28: =IFERROR(__xludf.DUMMYFUNCTION("""COMPUTED_VALUE"""),43) -> 43 | C28: =IFERROR(__xludf.DUMMYFUNCTION("INDEX(RECETAS!E:E, MAX(FILTER(ROW(RECETAS!A:A), RECETAS!A:A=A28)) + 1)"),758.1) -> 758.1 | D28: =C28*B28 -> 32598.3
A29: =IFERROR(__xludf.DUMMYFUNCTION("""COMPUTED_VALUE"""),"PINTA DE CERVEZA") -> PINTA DE CERVEZA | B29: =IFERROR(__xludf.DUMMYFUNCTION("""COMPUTED_VALUE"""),2) -> 2 | C29: =IFERROR(__xludf.DUMMYFUNCTION("INDEX(RECETAS!E:E, MAX(FILTER(ROW(RECETAS!A:A), RECETAS!A:A=A29)) + 1)"),1899.93933333333) -> 1899.9393 | D29: =C29*B29 -> 3799.8787
A30: =IFERROR(__xludf.DUMMYFUNCTION("""COMPUTED_VALUE"""),"PORCION DE PAPAS") -> PORCION DE PAPAS | B30: =IFERROR(__xludf.DUMMYFUNCTION("""COMPUTED_VALUE"""),19) -> 19 | C30: =IFERROR(__xludf.DUMMYFUNCTION("INDEX(RECETAS!E:E, MAX(FILTER(ROW(RECETAS!A:A), RECETAS!A:A=A30)) + 1)"),2292.92034615384) -> 2292.9203 | D30: =C30*B30 -> 43565.487
A31: =IFERROR(__xludf.DUMMYFUNCTION("""COMPUTED_VALUE"""),"PORCION DE PAPAS CON CHEDDAR Y BACON") -> PORCION DE PAPAS CON CHEDDAR Y BACON | B31: =IFERROR(__xludf.DUMMYFUNCTION("""COMPUTED_VALUE"""),6) -> 6 | C31: =IFERROR(__xludf.DUMMYFUNCTION("INDEX(RECETAS!E:E, MAX(FILTER(ROW(RECETAS!A:A), RECETAS!A:A=A31)) + 1)"),3229.7962032967) -> 3229.7962 | D31: =C31*B31 -> 19378.777
A32: =IFERROR(__xludf.DUMMYFUNCTION("""COMPUTED_VALUE"""),"PORCION DE PAPAS Y CHEDDAR") -> PORCION DE PAPAS Y CHEDDAR | B32: =IFERROR(__xludf.DUMMYFUNCTION("""COMPUTED_VALUE"""),7) -> 7 | C32: =IFERROR(__xludf.DUMMYFUNCTION("INDEX(RECETAS!E:E, MAX(FILTER(ROW(RECETAS!A:A), RECETAS!A:A=A32)) + 1)"),2948.1332032967) -> 2948.1332 | D32: =C32*B32 -> 20636.932
A33: =IFERROR(__xludf.DUMMYFUNCTION("""COMPUTED_VALUE"""),"POSTRE CHOCOTORTA") -> POSTRE CHOCOTORTA | B33: =IFERROR(__xludf.DUMMYFUNCTION("""COMPUTED_VALUE"""),13) -> 13 | C33: =IFERROR(__xludf.DUMMYFUNCTION("INDEX(RECETAS!E:E, MAX(FILTER(ROW(RECETAS!A:A), RECETAS!A:A=A33)) + 1)"),2800) -> 2800 | D33: =C33*B33 -> 36400
A34: =IFERROR(__xludf.DUMMYFUNCTION("""COMPUTED_VALUE"""),"POSTRE OREO") -> POSTRE OREO | B34: =IFERROR(__xludf.DUMMYFUNCTION("""COMPUTED_VALUE"""),12) -> 12 | C34: =IFERROR(__xludf.DUMMYFUNCTION("INDEX(RECETAS!E:E, MAX(FILTER(ROW(RECETAS!A:A), RECETAS!A:A=A34)) + 1)"),2800) -> 2800 | D34: =C34*B34 -> 33600
A35: =IFERROR(__xludf.DUMMYFUNCTION("""COMPUTED_VALUE"""),"PULLED PORK") -> PULLED PORK | B35: =IFERROR(__xludf.DUMMYFUNCTION("""COMPUTED_VALUE"""),63) -> 63 | C35: =IFERROR(__xludf.DUMMYFUNCTION("INDEX(RECETAS!E:E, MAX(FILTER(ROW(RECETAS!A:A), RECETAS!A:A=A35)) + 1)"),2652.60312106293) -> 2652.6031 | D35: =C35*B35 -> 167114
A36: =IFERROR(__xludf.DUMMYFUNCTION("""COMPUTED_VALUE"""),"SEVEN-UP") -> SEVEN-UP | B36: =IFERROR(__xludf.DUMMYFUNCTION("""COMPUTED_VALUE"""),126) -> 126 | C36: =IFERROR(__xludf.DUMMYFUNCTION("INDEX(RECETAS!E:E, MAX(FILTER(ROW(RECETAS!A:A), RECETAS!A:A=A36)) + 1)"),758.113333333333) -> 758.11333 | D36: =C36*B36 -> 95522.28
A37: =IFERROR(__xludf.DUMMYFUNCTION("""COMPUTED_VALUE"""),"SWEET BACON BURGER") -> SWEET BACON BURGER | B37: =IFERROR(__xludf.DUMMYFUNCTION("""COMPUTED_VALUE"""),31) -> 31 | C37: =IFERROR(__xludf.DUMMYFUNCTION("INDEX(RECETAS!E:E, MAX(FILTER(ROW(RECETAS!A:A), RECETAS!A:A=A37)) + 1)"),5148.53157939627) -> 5148.5316 | D37: =C37*B37 -> 159604.48
A38: =IFERROR(__xludf.DUMMYFUNCTION("""COMPUTED_VALUE"""),"SWEET ONION") -> SWEET ONION | B38: =IFERROR(__xludf.DUMMYFUNCTION("""COMPUTED_VALUE"""),68) -> 68 | C38: =IFERROR(__xludf.DUMMYFUNCTION("INDEX(RECETAS!E:E, MAX(FILTER(ROW(RECETAS!A:A), RECETAS!A:A=A38)) + 1)"),5183.03047939627) -> 5183.0305 | D38: =C38*B38 -> 352446.07
A39: =IFERROR(__xludf.DUMMYFUNCTION("""COMPUTED_VALUE"""),"TASTY WLB") -> TASTY WLB | B39: =IFERROR(__xludf.DUMMYFUNCTION("""COMPUTED_VALUE"""),41) -> 41 | C39: =IFERROR(__xludf.DUMMYFUNCTION("INDEX(RECETAS!E:E, MAX(FILTER(ROW(RECETAS!A:A), RECETAS!A:A=A39)) + 1)"),5411.03157939627) -> 5411.0316 | D39: =C39*B39 -> 221852.29
A40: =IFERROR(__xludf.DUMMYFUNCTION("""COMPUTED_VALUE"""),"TRIPLE CHEESE BACON") -> TRIPLE CHEESE BACON | B40: =IFERROR(__xludf.DUMMYFUNCTION("""COMPUTED_VALUE"""),64) -> 64 | C40: =IFERROR(__xludf.DUMMYFUNCTION("INDEX(RECETAS!E:E, MAX(FILTER(ROW(RECETAS!A:A), RECETAS!A:A=A40)) + 1)"),6830.32040995182) -> 6830.3204 | D40: =C40*B40 -> 437140.51
A41: =IFERROR(__xludf.DUMMYFUNCTION("""COMPUTED_VALUE"""),"VEGGIE BURGER") -> VEGGIE BURGER | B41: =IFERROR(__xludf.DUMMYFUNCTION("""COMPUTED_VALUE"""),26) -> 26 | C41: =IFERROR(__xludf.DUMMYFUNCTION("INDEX(RECETAS!E:E, MAX(FILTER(ROW(RECETAS!A:A), RECETAS!A:A=A41)) + 1)"),2674.4117877296) -> 2674.4118 | D41: =C41*B41 -> 69534.706
C42: =IFERROR(__xludf.DUMMYFUNCTION("INDEX(RECETAS!E:E, MAX(FILTER(ROW(RECETAS!A:A), RECETAS!A:A=A42)) + 1)"),"") | D42: =C42*B42 -> #VALUE!
C43: =SUM(Tabla_4[COSTO UNITARIO]) -> 122558.62 | D43: =SUM(D4:D42) -> #VALUE! | E43: =E4+F4 -> #REF! | F43: =D43/E43 -> #VALUE!

Sheet ResumenVentas
A1: Producto | B1: Cantidad
A2: MOBY DICK | B2: 1
A3: AMERICAN BURGER | B3: 1
A4: PEPSI | B4: 1
A5: CHEESE BACON | B5: 1
A6: MOBY DICK | B6: 1
A7: SEVEN-UP | B7: 1
A8: PEPSI | B8: 1
A9: HUMPTY BURGER | B9: 1
A10: PEPSI | B10: 1
A11: AMERICAN BURGER | B11: 1
A12: AMERICAN BURGER | B12: 1
A13: EXTRA MEDALLON | B13: -1
... A119: SEVEN-UP | B119: 1
A120: SEVEN-UP
A121: PORCION DE PAPAS | B121: 1
A122: AGUA MINERAL | B122: 1
A123: DOBLE CUARTO | B123: 1
A124: PULLED PORK | B124: 1
A125: CHEESE BACON | B125: 1
A126: AMERICAN BURGER | B126: 1
A127: MIRINDA | B127: 1
A128: MIRINDA | B128: 1
A129: MIGI BURGER | B129: 1
A130: PEPSI | B130: 1
A131: CHEESE BURGER | B131: 1
A132: CHEESE BURGER | B132: 1
... A451: EXTRA MEDALLON | B451: -1
A452: MOBY DICK
A453: PEPSI | B453: 1
A454: SWEET BACON BURGER | B454: 1
A455: MOBY DICK | B455: 1
A456: PULLED PORK | B456: 1
A457: AGUA MINERAL | B457: 2
A458: HUMPTY BURGER | B458: 1
A459: BOTELLA DE CERVEZA | B459: 1
A460: MEDIA PINTA DE CERVEZA | B460: 1
A461: MIGI BURGER | B461: 1
A462: EXTRA MEDALLON | B462: -1
A463: EXTRA MEDALLON | B463: -1
A464: MIGI BURGER | B464: 1
... A1787: CHEESE BACON | B1787: 1

Sheet EERR
A1: RUBRO | B1: PRECIOS | C1: % PORCENTAJE | E1: Periodo | F1: Facturación
A2: FACTURACION ESTIMADA | B2: 18721000 | C2: =C4*100 -> #VALUE! | E2: agosto 2025 | F2: ='Agosto 2025'!E34 -> 21045137
A3: punto de equilibrio | B3: =B29 / (1 - (C2 / 100)) -> #VALUE! | C3: =C2 -> #VALUE! | E3: septiembre 2025 | F3: =#REF! -> #REF!
A4: CMV | B4: =B2*C4 -> #VALUE! | C4: =Tabla_4[[#Totals],[CMV ]] -> #VALUE! | E4: octubre 2025 | F4: =#REF! -> #REF!
A5: ALQUILER | B5: 3000000 | C5: =(B5/$B$2)*100 -> 16.024785 | E5: noviembre 2025 | F5: =#REF! -> #REF!
A6: EDELAP | B6: 979000 | C6: =(B6/$B$2)*100 -> 5.2294215 | E6: diciembre 2025 | F6: =#REF! -> #REF!
A7: GAS | B7: 180000 | C7: =(B7/$B$2)*100 -> 0.9614871 | E7: enero 2026 | F7: =#REF! -> #REF!
A8: SEGURO | B8: 120000 | C8: =(B8/$B$2)*100 -> 0.6409914 | E8: febrero 2026 | F8: =#REF! -> #REF!
A9: ALARMA | B9: 70000 | C9: =(B9/$B$2)*100 -> 0.37391165
A10: SISTEMA DE PUNTOS | B10: 50000 | C10: =(B10/$B$2)*100 -> 0.26707975
A11: RESTO SIMPLE | B11: 20500 | C11: =(B11/$B$2)*100 -> 0.1095027
A12: ACEITE | B12: 180000 | C12: =(B12/$B$2)*100 -> 0.9614871
A13: VERDULERIA | B13: 120000 | C13: =(B13/$B$2)*100 -> 0.6409914
A14: PAPELERIA | B14: 150000 | C14: =(B14/$B$2)*100 -> 0.80123925
A15: AGUZETA | B15: 780000 | C15: =(B15/$B$2)*100 -> 4.1664441
A16: PIXET | B16: 81000 | C16: =(B16/$B$2)*100 -> 0.4326692
A17: CINET | B17: 101000 | C17: =(B17/$B$2)*100 -> 0.5395011
A18: Gastos Fijos | B18: =SUM(B5:B17) -> 5831500 | C18: =SUM(C5:C17) -> 31.149511
A19: Encargado | B19: 900000 | C19: =(B19/$B$2)*100 -> 4.8074355
A20: Emplado 4 hs | B20: 460000 | C20: =(B20/$B$2)*100 -> 2.4571337
A21: Emplado 4 hs | B21: 460000 | C21: =(B21/$B$2)*100 -> 2.4571337
A22: Emplado 4 hs | B22: 460000 | C22: =(B22/$B$2)*100 -> 2.4571337
A23: Emplado 4 hs | B23: 460000 | C23: =(B23/$B$2)*100 -> 2.4571337
A24: Emplado 4 hs | B24: 460000 | C24: =(B24/$B$2)*100 -> 2.4571337
A25: 931 ARCA | B25: 600000 | C25: =(B25/$B$2)*100 -> 3.204957
A26: Total Sueldos | B26: =SUM(B19:B25) -> 3800000 | C26: =SUM(C19:C25) -> 20.298061
A27: IVA | B27: 500000 | C27: =(B27/$B$2)*100 -> 2.6707975
A28: IIBB | B28: 150000 | C28: =(B28/$B$2)*100 -> 0.80123925
A29: TOTAL GASTOS | B29: =B28+B27+B26+B18 -> 10281500 | C29: =C26+C18+C28+C27+C28 -> 55.720848
A30: GASTOS + CMV | B30: =B29+B4 -> #VALUE!
A31: RESULTADO | B31: =B2-B30 -> #VALUE! | C31: =(B31/$B$2)*100 -> #VALUE!
B32: =B4-B31 -> #VALUE! | C32: =(B32/$B$2)*100 -> #VALUE!

Sheet Base de Datos
B2: Medallon 110 gr | D2: CHEESE BACON | F2: Blend de carne
B3: Medallon 80 gr | D3: CHEESE BURGER | F3: Bondiola de cerdo
B4: Medallon Veggie | D4: DOBLE CUARTO | F4: Pan chico de papa TBB
B5: Bacon | D5: ONION RINGS BURGER | F5: Pan TBB
B6: Cebolla caramelizada | D6: TASTY WLB | F6: Papas bastón SIMPLOT Extra Crunch
B7: Cebolla picada | D7: SWEET ONION | F7: Nuggets de Pollo
B8: Queso Dambo | D8: MIGI BURGER | F8: Aros de Cebolla
B9: Cheedar feteado Milkaut | D9: JIMMY BURGER | F9: Bacon
B10: Cebolla Crispy | D10: TRIPLE CHEESE BACON | F10: Cheedar feteado Milkaut
B11: Pepinillo | D11: MOBY DICK | F11: Postre Oreo
B12: Individual | D12: PULLED PORK | F12: Postre Chocotorta
B13: Mostaza | D13: AMERICAN BURGER | F13: Parafinado Zoso LOTTA Burgers
... B16: Bebida lata | D16: CRISPY BURGER | F16: Medallon Veggie
B17: Papel Aluminio | D17: HUMPTY BURGER
B18: Parafinado Zoso LOTTA Burgers | D18: SWEET BACON BURGER
B19: Sobre de papas fritas LOTTA | D19: PORCION DE PAPAS
B20: Aros de Cebolla | D20: PORCION DE PAPAS Y CHEDDAR
B21: Barbacoa | D21: PORCION DE PAPAS CON CHEDDAR Y BACON
B22: Lechuga | D22: AROS DE CEBOLLA
B23: Tomate | D23: PEPSI
B24: Salsa TASTY | D24: PEPSI BLACK
B25: Pepino en vinagre | D25: MIRINDA
B26: Pan TBB | D26: SEVEN-UP
B27: Cerveza tirada | D27: AGUA MINERAL
B28: Dips con tapa | D28: AGUA POMELO H20
... B48: Cerveza tirada | D48: BONDIOLA BAJA
B49: Cerveza tirada
B50: Seven-up
B51: Agua mineral
B52: Agua Pomelo H20
B53: Agua Limón H20
B54: Agua Manzana H20
B55: Media Pinta de Cerveza
B56: Nuggets de Pollo
B57: Postre Oreo
B58: Postre Chocotorta
B59: Pinta de Cerveza
B60: Botella de Cerveza
... B67: Blend de carne PREMIUM

Sheet Agosto 2025
B1: Nro | C1: turno A | D1: turno B | E1: total | F1: día
B3: 1 | C3: 217600.02 | D3: 289930 | E3: =C3+D3 -> 507530.02 | F3: Viernes
B4: 2 | C4: 678800.01 | D4: 634500.03 | E4: =C4+D4 -> 1313300 | F4: sábado
B5: 3 | C5: 453800 | D5: 557900.03 | E5: =C5+D5 -> 1011700 | F5: domingo
B6: 4 | C6: 386400.03 | D6: 277100.04 | E6: =C6+D6 -> 663500.07 | F6: lunes
B7: 5 | C7: 305600 | D7: 260800.01 | E7: =C7+D7 -> 566400.01 | F7: martes
B8: 6 | C8: 471000.01 | D8: 308101.03 | E8: =C8+D8 -> 779101.04 | F8: miércoles
B9: 7 | C9: 330000.03 | D9: 275980 | E9: =C9+D9 -> 605980.03 | F9: jueves
B10: 8 | C10: 442000.01 | D10: 619270.03 | E10: =C10+D10 -> 1061270 | F10: viernes
B11: 9 | C11: 400900 | D11: 666200.02 | E11: =C11+D11 -> 1067100 | F11: sábado
B12: 10 | C12: 449700 | D12: 354200.02 | E12: =C12+D12 -> 803900.02 | F12: domingo
B13: 11 | C13: 378100 | D13: 107050 | E13: =C13+D13 -> 485150 | F13: lunes
B14: 12 | C14: 160800 | D14: 271000 | E14: =C14+D14 -> 431800 | F14: martes
... B33: 31 | C33: 104100 | D33: 350800 | E33: =C33+D33 -> 454900 | F33: domingo
B34: total | C34: =SUM(C3:C33) -> 10075856 | D34: =SUM(D3:D33) -> 10969281 | E34: =SUM(E3:E33) -> 21045137
C35: =IF(COUNT(C3:C33)=0, "", AVERAGE(C3:C33)) -> 325027.62 | D35: =IF(COUNT(D3:D33)=0, "", AVERAGE(D3:D33)) -> 353847.78 | E35: =D35+C35 -> 678875.4 | F35: Promedios
E36: =E35*31 -> 21045137 | F36: Estimada

Sheet Julio 2025
B1: Nro | C1: turno A | D1: turno B | E1: total | F1: día
B2: 1 | C2: 577750.02 | D2: 462500.06 | E2: =D2+C2 -> 1040250.1 | F2: Martes
B3: 2 | C3: 462100.02 | D3: 292500 | E3: =D3+C3 -> 754600.02 | F3: Miércoles
B4: 3 | C4: 547250.05 | D4: 743000.06 | E4: =D4+C4 -> 1290250.1 | F4: Jueves
B5: 4 | C5: 509500.01 | D5: 733060.07 | E5: =D5+C5 -> 1242560.1 | F5: Viernes
B6: 5 | C6: 848350.04 | D6: 806490.04 | E6: =D6+C6 -> 1654840.1 | F6: Sábado
B7: 6 | C7: 891800.11 | D7: 423890.01 | E7: =D7+C7 -> 1315690.1 | F7: Domingo
B8: 7 | C8: 539580.07 | D8: 290000.03 | E8: =D8+C8 -> 829580.1 | F8: Lunes
B9: 8 | C9: 409950.02 | D9: 516800.02 | E9: =D9+C9 -> 926750.04 | F9: Martes
B10: 9 | C10: 444050.03 | D10: 594600.03 | E10: =D10+C10 -> 1038650.1 | F10: Miércoles
B11: 10 | C11: 327300.03 | D11: 277100 | E11: =D11+C11 -> 604400.03 | F11: Jueves
B12: 11 | C12: 369700.01 | D12: 554032.03 | E12: =D12+C12 -> 923732.04 | F12: Viernes
B13: 12 | C13: 315150.01 | D13: 544750.03 | E13: =D13+C13 -> 859900.04 | F13: Sábado
... B22: 21 | C22: 342400.01 | D22: 471300 | E22: =D22+C22 -> 813700.01 | F22: Lunes
B23: 22 | C23: 416800.01 | D23: 185230 | E23: =C23+D23 -> 602030.01 | F23: Martes
B24: 23 | C24: 174200.01 | D24: 292200.01 | E24: =D24+C24 -> 466400.02 | F24: Miércoles
B25: 24 | C25: 633350.07 | D25: 311900.01 | E25: =D25+C25 -> 945250.08 | F25: Jueves
B26: 25 | C26: 388400.01 | D26: 735200.01 | E26: =C26+D26 -> 1123600 | F26: Viernes
B27: 26 | C27: 480700.03 | D27: 434400 | E27: =C27+D27 -> 915100.03 | F27: Sábado
B28: 27 | C28: 167100.01 | D28: 466500 | E28: =C28+D28 -> 633600.01 | F28: Domingo
B29: 28 | C29: 160900.04 | D29: 426700 | E29: =C29+D29 -> 587600.04 | F29: Lunes
B30: 29 | C30: 433750.02 | D30: 267100 | E30: =C30+D30 -> 700850.02 | F30: Martes
B31: 30 | C31: 297070.02 | D31: 574000 | E31: =C31+D31 -> 871070.02 | F31: Miércoles
B32: 31 | C32: 495900 | D32: 429900 | E32: =C32+D32 -> 925800 | F32: Jueves
B33: total | C33: =SUM(C2:C32) -> 13410391 | D33: =SUM(D2:D32) -> 13970653 | E33: =SUM(E2:E32) -> 27381043
C34: =IF(COUNT(C2:C32)=0, "", AVERAGE(C2:C32)) -> 432593.25 | D34: =IF(COUNT(D3:D32)=0, "", AVERAGE(D2:D32)) -> 450666.21 | E34: =D34+C34 -> 883259.46 | F34: Promedios
E35: =E34*31 -> 27381043 | F35: Estimada

Sheet Junio 2025
B1: Nro | C1: turno A | D1: turno B | E1: total | F1: día
B2: 1 | C2: 0 | D2: 242110.02 | E2: =D2+C2 -> 242110.02 | F2: domingo
B3: 2 | C3: 241300 | D3: 193600 | E3: =D3+C3 -> 434900 | F3: lunes
B4: 3 | C4: 247658.02 | D4: 559980.01 | E4: =D4+C4 -> 807638.03 | F4: martes
B5: 4 | C5: 264250 | D5: 363550 | E5: =D5+C5 -> 627800 | F5: miércoles
B6: 5 | C6: 398900 | D6: 756706.01 | E6: =D6+C6 -> 1155606 | F6: jueves
B7: 6 | C7: 655200 | D7: 839490.01 | E7: =D7+C7 -> 1494690 | F7: viernes
B8: 7 | C8: 568300 | D8: 1284300 | E8: =D8+C8 -> 1852600 | F8: sábado
B9: 8 | C9: 288650 | D9: 423459 | E9: =D9+C9 -> 712109 | F9: domingo
B10: 9 | C10: 511161.6 | D10: 346100 | E10: =D10+C10 -> 857261.6 | F10: lunes
B11: 10 | C11: 451200 | D11: 162980 | E11: =D11+C11 -> 614180 | F11: martes
B12: 11 | C12: 378650 | D12: 295000 | E12: =D12+C12 -> 673650 | F12: miércoles
B13: 12 | C13: 514400 | D13: 314601 | E13: =D13+C13 -> 829001 | F13: jueves
... B20: 19 | C20: 427200.02 | D20: 549880.05 | E20: =D20+C20 -> 977080.07 | F20: jueves
B21: 20 | C21: 534000.02 | D21: 643100.03 | E21: 0 | F21: viernes
B22: 21 | C22: 446100.01 | D22: 441230.01 | E22: =D22+C22 -> 887330.02 | F22: sábado
B23: 22 | C23: 336500.01 | D23: 377350 | E23: =C23+D23 -> 713850.01 | F23: domingo
B24: 23 | C24: 162900 | D24: 258500.02 | E24: =D24+C24 -> 421400.02 | F24: lunes
B25: 24 | C25: 400400.04 | D25: 368100 | E25: =D25+C25 -> 768500.04 | F25: martes
B26: 25 | C26: 489000.01 | D26: 170410.01 | E26: =C26+D26 -> 659410.02 | F26: miércoles
B27: 26 | C27: 425600.01 | D27: 188800.02 | E27: =C27+D27 -> 614400.03 | F27: jueves
B28: 27 | C28: 284930.01 | D28: 462800.03 | E28: =C28+D28 -> 747730.04 | F28: viernes
B29: 28 | C29: 479250.01 | D29: 483760.03 | E29: =C29+D29 -> 963010.04 | F29: sábado
B30: 29 | C30: 172150 | D30: 390540.05 | E30: =C30+D30 -> 562690.05 | F30: domingo
B31: 30 | C31: 351150.03 | D31: 173200 | E31: =C31+D31 -> 524350.03 | F31: lunes
B32: total | C32: =SUM(C2:C31) -> 11276291 | D32: =SUM(D2:D31) -> 12810546 | E32: =SUM(E2:E31) -> 22909737
C33: =IF(COUNT(C3:C31)=0, "", AVERAGE(C3:C31)) -> 388837.61 | D33: =IF(COUNT(C3:C31)=0, "", AVERAGE(C3:C31)) -> 388837.61 | E33: =D33+C33 -> 777675.23 | F33: Promedios
E34: =E33*30 -> 23330257 | F34: Estimada

Sheet EEMM-COMPETENCIA
A1: Producto elaborado | B1: Insumo | C1: Cantidad | D1: Costo Total | F1: Producto elaborado | G1: Insumo | H1: Cantidad | I1: Costo Total
A2: LA NUEVA | B2: Pan Brioche | C2: 1 | F2: GRILLED ONION | G2: Pan Brioche | H2: 1
A3: LA NUEVA | B3: Medallon de 120 gr | C3: 2 | F3: GRILLED ONION | G3: Medallon de 110 gr | H3: 1
A4: LA NUEVA | B4: Cheddar feteado | C4: 4 | F4: GRILLED ONION | G4: Cheddar feteado | H4: 4
A5: LA NUEVA | B5: Cebolla Caramelizada | C5: 20 | F5: GRILLED ONION | G5: Cebolla picada | H5: 10
A6: LA NUEVA | B6: Bacon | C6: 60 | F6: GRILLED ONION | G6: Pepinos | H6: 3
A7: LA NUEVA | B7: Salsa Alioli | C7: 5 | F7: GRILLED ONION | G7: Salsa Burgas | H7: 5
A8: LA NUEVA | B8: Papas pequeñas | C8: 1 | F8: GRILLED ONION | G8: Papas pequeñas | H8: 1
D9: 12580 | I9: 13600
A10: LA MARY | B10: Pan Brioche | C10: 1 | F10: AMERICAN BURGER | G10: Pan Brioche | H10: 1
A11: LA MARY | B11: Medallon de 120 gr | C11: 2 | F11: AMERICAN BURGER | G11: Medallon de 110 gr | H11: 2
A12: LA MARY | B12: Cheddar feteado | C12: 4 | F12: AMERICAN BURGER | G12: Cheddar feteado | H12: 4
A13: LA MARY | B13: Cebolla Crispy | C13: 20 | F13: AMERICAN BURGER | G13: Cebolla picada | H13: 10
A14: LA MARY | B14: Bacon | C14: 60 | F14: AMERICAN BURGER | G14: Bacon | H14: 60
A15: LA MARY | B15: Salsa Mil Islas | C15: 5 | F15: AMERICAN BURGER | G15: Salsa burgas | H15: 5
A16: LA MARY | B16: Papas pequeñas | C16: 1 | F16: AMERICAN BURGER | G16: Papas pequeñas | H16: 1
D17: 15300 | I17: 13600
A18: LA LILY | B18: Pan Brioche | C18: 1 | F18: BBQ RINGS | G18: Pan Brioche | H18: 1
A19: LA LILY | B19: Medallon de 120 gr | C19: 2 | F19: BBQ RINGS | G19: Medallon de 120 gr | H19: 2
A20: LA LILY | B20: Cheddar feteado | C20: 4 | F20: BBQ RINGS | G20: Cheddar feteado | H20: 3
A21: LA LILY | B21: Pickles de pepino | C21: 3 | F21: BBQ RINGS | G21: Bacon | H21: 60
A22: LA LILY | B22: Bacon | C22: 60 | F22: BBQ RINGS | G22: Salsa BBQ | H22: 5
A23: LA LILY | B23: Salsa Mil Islas | C23: 5 | F23: BBQ RINGS | G23: Aros de Cebolla | H23: 3
A24: LA LILY | B24: Papas pequeñas | C24: 1 | F24: BBQ RINGS | G24: Papas pequeñas | H24: 1
D25: 15100 | I25: 13800
A26: LA GLORIA | B26: Pan Brioche | C26: 1 | F26: BURGA CLASIC | G26: Pan Brioche | H26: 1
A27: LA GLORIA | B27: Medallon de 120 gr | C27: 2 | F27: BURGA CLASIC | G27: Medallon de 110 gr | H27: 2
A28: LA GLORIA | B28: Queso Dambo | C28: 2 | F28: BURGA CLASIC | G28: Cheddar feteado | H28: 4
A29: LA GLORIA | B29: Salsa Roquefort | C29: 5 | F29: BURGA CLASIC | G29: Bacon | H29: 40
A30: LA GLORIA | B30: Cebolla Caramelizada | C30: 20 | F30: BURGA CLASIC | G30: Cebolla Caramelizada | H30: 20
A31: LA GLORIA | B31: Hongos | C31: 5 | F31: BURGA CLASIC | G31: Papas pequeñas | H31: 1
A32: LA GLORIA | B32: Nuez | C32: 5 | I32: 13500
A33: LA GLORIA | B33: Papas pequeñas | C33: 1 | F33: CHEESE BACON | G33: Medallon de 110 gr | H33: 2
D34: 14900 | F34: CHEESE BACON | G34: Cheddar feteado | H34: 4
A35: TASTY | B35: Pan Brioche | C35: 1 | F35: CHEESE BACON | G35: Bacon | H35: 60
A36: TASTY | B36: Medallon de 120 gr | C36: 2 | F36: CHEESE BACON | G36: Papas pequeñas | H36: 1
A37: TASTY | B37: Cheddar feteado | C37: 4 | I37: 13000
A38: TASTY | B38: Lechuga | C38: 10 | F38: CRISPY BURGER | G38: Medallon de 110 gr | H38: 2
A39: TASTY | B39: Tomate | C39: 20 | F39: CRISPY BURGER | G39: Cheddar feteado | H39: 4
A40: TASTY | B40: Bacon cortado | C40: 5 | F40: CRISPY BURGER | G40: Cebolla Crispy | H40: 5
A41: TASTY | B41: Salsa Tasty | C41: 5 | F41: CRISPY BURGER | G41: Bacon | H41: 60
A42: TASTY | B42: Papas pequeñas | C42: 1 | F42: CRISPY BURGER | G42: Salsa burgas | H42: 5
D43: 14700 | F43: CRISPY BURGER | G43: Papas pequeñas | H43: 1
A44: LA LOCAL | B44: Pan Brioche | C44: 1 | I44: 13600
A45: LA LOCAL | B45: Medallon de 120 gr | C45: 2 | F45: CUARTO DE LIBRA | G45: Medallon de 110 gr | H45: 2
A46: LA LOCAL | B46: Cheddar feteado | C46: 4 | F46: CUARTO DE LIBRA | G46: Cheddar feteado | H46: 4
A47: LA LOCAL | B47: Mermelada de Bacon | C47: 5 | F47: CUARTO DE LIBRA | G47: Cebolla picada | H47: 5
A48: LA LOCAL | B48: Cebolla Crispy | C48: 5 | F48: CUARTO DE LIBRA | G48: Mostaza | H48: 5
A49: LA LOCAL | B49: Mayonesa ahumada | C49: 5 | F49: CUARTO DE LIBRA | G49: Ketchup | H49: 5
A50: LA LOCAL | B50: Papas pequeñas | C50: 1 | F50: CUARTO DE LIBRA | G50: Papas pequeñas | H50: 1
D51: 14700 | I51: 13200
A52: LOLOCHA | B52: Pan Brioche | C52: 1 | F52: STACKED | G52: Medallon de 110 gr | H52: 2
A53: LOLOCHA | B53: Medallon de 120 gr | C53: 2 | F53: STACKED | G53: Cheddar feteado | H53: 4
A54: LOLOCHA | B54: Cheddar feteado | C54: 4 | F54: STACKED | G54: Bacon | H54: 60
A55: LOLOCHA | B55: Cebolla a la plancha | C55: 10 | F55: STACKED | G55: Salsa Stacked | H55: 5
A56: LOLOCHA | B56: Salsa Big Mac | C56: 5 | F56: STACKED | G56: Papas pequeñas | H56: 1
A57: LOLOCHA | B57: Papas pequeñas | C57: 1 | I57: 13700
D58: 14500 | F58: TRIPLE CHEESE BACON | G58: Medallon de 110 gr | H58: 3
A59: DOBLE CUARTO DE TULA | B59: Pan Brioche | C59: 1 | F59: TRIPLE CHEESE BACON | G59: Cheddar feteado | H59: 4
A60: DOBLE CUARTO DE TULA | B60: Medallon de 120 gr | C60: 2 | F60: TRIPLE CHEESE BACON | G60: Bacon | H60: 60
A61: DOBLE CUARTO DE TULA | B61: Cheddar feteado | C61: 4 | F61: TRIPLE CHEESE BACON | G61: Papas pequeñas | H61: 1
A62: DOBLE CUARTO DE TULA | B62: Cebolla cortada chiquita | C62: 5 | I62: 15200
A63: DOBLE CUARTO DE TULA | B63: Ketchup | C63: 5
A64: DOBLE CUARTO DE TULA | B64: Mostaza | C64: 5
A65: DOBLE CUARTO DE TULA | B65: Papas pequeñas | C65: 1
D66: 14500
A67: BIG BORZI | B67: Pan Brioche | C67: 1
A68: BIG BORZI | B68: Medallon de 120 gr | C68: 2
A69: BIG BORZI | B69: Cheddar feteado | C69: 4
A70: BIG BORZI | B70: Pickles de pepino | C70: 3
A71: BIG BORZI | B71: Lechuga crujiente | C71: 10
A72: BIG BORZI | B72: Cebolla en cubos | C72: 5
A73: BIG BORZI | B73: Salsa Big Mac | C73: 5
A74: BIG BORZI | B74: Papas pequeñas | C74: 1
D75: 14500
A76: LA NEGRA | B76: Pan Brioche | C76: 1
A77: LA NEGRA | B77: Medallon Smash con Cebolla 120 gr | C77: 2
A78: LA NEGRA | B78: Queso Gouda ahumado | C78: 5
A79: LA NEGRA | B79: Salsa de ajo negro | C79: 5
A80: LA NEGRA | B80: Papas pequeñas | C80: 1
D81: 14400
A82: RAMONA | B82: Pan de cabutia | C82: 1
A83: RAMONA | B83: Medallon simil carne | C83: 2
A84: RAMONA | B84: Muzzarella vegana | C84: 5
A85: RAMONA | B85: Cebolla Crispy | C85: 5
A86: RAMONA | B86: Lechuga | C86: 10
A87: RAMONA | B87: Tomate deshidratado | C87: 5
A88: RAMONA | B88: Pesto de albahaca | C88: 5
A89: RAMONA | B89: Papas pequeñas | C89: 1
D90: 13200
A91: LA TITA | B91: Pan Brioche | C91: 1
A92: LA TITA | B92: Medallon de 120 gr | C92: 2
A93: LA TITA | B93: Cheddar feteado | C93: 4
A94: LA TITA | B94: Cebolla cortada chiquita | C94: 5
A95: LA TITA | B95: Salsa mil islas | C95: 5
A96: LA TITA | B96: Papas pequeñas | C96: 1
D97: 14100
B98: PROMEDIO DE PRECIOS | D98: =AVERAGE(BORZI_BURGER[Costo Total]) -> 14373.333 | G98: PROMEDIO DE PRECIOS | I98: =AVERAGE(THE_BURGAS[Costo Total]) -> 13688.889
